{
  "baseURI": "https://dcjm.data.vlaanderen.be/ns/financiele-data/taxonomie#",
  "entities": [
    {
      "id": "https://dcjm.data.vlaanderen.be/ns/financiele-data/taxonomie#Code70/76A",
      "vocabularyLabel": {
        "nl": "Bedrijfsopbrengsten"
      },
      "applicationProfileLabel": {
        "nl": "Bedrijfsopbrengsten"
      },
      "vocabularyDefinition": {
        "nl": "Onder de bedrijfsopbrengsten wordt verstaan de opbrengsten die voortvloeien uit de normale exploitatie of uitbating van de organisatie."
      },
      "applicationProfileDefinition": {
        "nl": "Onder de bedrijfsopbrengsten wordt verstaan de opbrengsten die voortvloeien uit de normale exploitatie of uitbating van de organisatie."
      },
      "parents": [
        {
          "id": "https://dcjm.data.vlaanderen.be/ns/financiele-data/taxonomie#DCJMfeit",
          "vocabularyLabel": {
            "nl": "DCJMfeit"
          },
          "applicationProfileLabel": {
            "nl": "DCJMfeit"
          }
        }
      ],
      "scope": "https://data.vlaanderen.be/id/concept/scope/InPackage",
      "properties": [
        {
          "id": "https://dcjm.data.vlaanderen.be/ns/financiele-data/taxonomie#Bedrijfsopbrengsten.balanstype",
          "vocabularyLabel": {
            "nl": "balanstype"
          },
          "applicationProfileLabel": {
            "nl": "balanstype"
          },
          "vocabularyDefinition": {
            "nl": "TODO"
          },
          "applicationProfileDefinition": {
            "nl": "TODO"
          },
          "vocabularyUsageNote": {
            "nl": "Default waarde voor dit type Feit is \"krediet\"."
          },
          "applicationProfileUsageNote": {
            "nl": "Default waarde voor dit type Feit is \"krediet\"."
          },
          "scope": "https://data.vlaanderen.be/id/concept/scope/InPackage",
          "domain": "https://dcjm.data.vlaanderen.be/ns/financiele-data/taxonomie#Code70/76A",
          "range": {
            "id": "http://www.w3.org/2004/02/skos/core#Concept",
            "vocabularyLabel": {
              "nl": "BalansType"
            },
            "applicationProfileLabel": {
              "nl": "BalansType"
            }
          },
          "minCount": "1",
          "maxCount": "1"
        },
        {
          "id": "https://dcjm.data.vlaanderen.be/ns/financiele-data/taxonomie#rubriek",
          "vocabularyLabel": {
            "nl": "rubriek"
          },
          "applicationProfileLabel": {
            "nl": "rubriek"
          },
          "vocabularyDefinition": {
            "nl": "TODO"
          },
          "applicationProfileDefinition": {
            "nl": "TODO"
          },
          "vocabularyUsageNote": {
            "nl": "Default waarde voor dit type Feit is \"70/76A\"."
          },
          "applicationProfileUsageNote": {
            "nl": "Default waarde voor dit type Feit is \"70/76A\"."
          },
          "scope": "https://data.vlaanderen.be/id/concept/scope/InPackage",
          "domain": "https://dcjm.data.vlaanderen.be/ns/financiele-data/taxonomie#Code70/76A",
          "range": {
            "id": "http://www.w3.org/ns/adms#Identifier",
            "vocabularyLabel": {
              "nl": "Identificator"
            },
            "applicationProfileLabel": {
              "nl": "Identificator"
            }
          },
          "minCount": "1",
          "maxCount": "1"
        }
      ]
    },
    {
      "id": "https://dcjm.data.vlaanderen.be/ns/financiele-data/taxonomie#DCJMfeit",
      "vocabularyLabel": {
        "nl": "DCJMfeit"
      },
      "applicationProfileLabel": {
        "nl": "DCJMfeit"
      },
      "vocabularyDefinition": {
        "nl": "TODO"
      },
      "applicationProfileDefinition": {
        "nl": "TODO"
      },
      "parents": [
        {
          "id": "https://data.vlaanderen.be/ns/financiele-rapportering#Feit",
          "vocabularyLabel": {
            "nl": "Feit"
          },
          "applicationProfileLabel": {
            "nl": "Feit"
          }
        }
      ],
      "scope": "https://data.vlaanderen.be/id/concept/scope/InPackage",
      "properties": [
        {
          "id": "https://dcjm.data.vlaanderen.be/ns/financiele-data/taxonomie#DCJMfeit.balanstype",
          "vocabularyLabel": {
            "nl": "balanstype"
          },
          "applicationProfileLabel": {
            "nl": "balanstype"
          },
          "vocabularyDefinition": {
            "nl": "TODO"
          },
          "applicationProfileDefinition": {
            "nl": "TODO"
          },
          "scope": "https://data.vlaanderen.be/id/concept/scope/InPackage",
          "domain": "https://dcjm.data.vlaanderen.be/ns/financiele-data/taxonomie#DCJMfeit",
          "range": {
            "id": "http://www.w3.org/2004/02/skos/core#Concept",
            "vocabularyLabel": {
              "nl": "BalansType"
            },
            "applicationProfileLabel": {
              "nl": "BalansType"
            }
          },
          "minCount": "1",
          "maxCount": "1"
        },
        {
          "id": "https://dcjm.data.vlaanderen.be/ns/financiele-data/taxonomie#DCJMfeit.concept",
          "vocabularyLabel": {
            "nl": "concept"
          },
          "applicationProfileLabel": {
            "nl": "concept"
          },
          "vocabularyDefinition": {
            "nl": "TODO"
          },
          "applicationProfileDefinition": {
            "nl": "TODO"
          },
          "scope": "https://data.vlaanderen.be/id/concept/scope/InPackage",
          "domain": "https://dcjm.data.vlaanderen.be/ns/financiele-data/taxonomie#DCJMfeit",
          "range": {
            "id": "https://data.vlaanderen.be/ns/financiele-rapportering#Concept",
            "vocabularyLabel": {
              "nl": "Concept"
            },
            "applicationProfileLabel": {
              "nl": "Concept"
            }
          },
          "minCount": "0",
          "maxCount": "1"
        },
        {
          "id": "https://dcjm.data.vlaanderen.be/ns/financiele-data/taxonomie#context",
          "vocabularyLabel": {
            "nl": "context"
          },
          "applicationProfileLabel": {
            "nl": "context"
          },
          "vocabularyDefinition": {
            "nl": "TODO"
          },
          "applicationProfileDefinition": {
            "nl": "TODO"
          },
          "scope": "https://data.vlaanderen.be/id/concept/scope/InPackage",
          "domain": "https://dcjm.data.vlaanderen.be/ns/financiele-data/taxonomie#DCJMfeit",
          "range": {
            "id": "https://dcjm.data.vlaanderen.be/ns/financiele-data/taxonomie#HuidigePeriode",
            "vocabularyLabel": {
              "nl": "HuidigePeriode"
            },
            "applicationProfileLabel": {
              "nl": "HuidigePeriode"
            }
          }
        },
        {
          "id": "https://dcjm.data.vlaanderen.be/ns/financiele-data/taxonomie#orde",
          "vocabularyLabel": {
            "nl": "orde"
          },
          "applicationProfileLabel": {
            "nl": "orde"
          },
          "vocabularyDefinition": {
            "nl": "TODO"
          },
          "applicationProfileDefinition": {
            "nl": "TODO"
          },
          "scope": "https://data.vlaanderen.be/id/concept/scope/InPackage",
          "domain": "https://dcjm.data.vlaanderen.be/ns/financiele-data/taxonomie#DCJMfeit",
          "range": {
            "id": "http://www.w3.org/2001/XMLSchema#integer",
            "vocabularyLabel": {
              "nl": "Integer"
            },
            "applicationProfileLabel": {
              "nl": "Integer"
            }
          },
          "minCount": "0",
          "maxCount": "1"
        },
        {
          "id": "https://dcjm.data.vlaanderen.be/ns/financiele-data/taxonomie#DCJMfeit.rapport",
          "vocabularyLabel": {
            "nl": "rapport"
          },
          "applicationProfileLabel": {
            "nl": "rapport"
          },
          "vocabularyDefinition": {
            "nl": "TODO"
          },
          "applicationProfileDefinition": {
            "nl": "TODO"
          },
          "scope": "https://data.vlaanderen.be/id/concept/scope/InPackage",
          "domain": "https://dcjm.data.vlaanderen.be/ns/financiele-data/taxonomie#DCJMfeit",
          "range": {
            "id": "https://data.vlaanderen.be/ns/financiele-rapportering#FinancieelRapport",
            "vocabularyLabel": {
              "nl": "FinancieelRapport"
            },
            "applicationProfileLabel": {
              "nl": "FinancieelRapport"
            }
          },
          "minCount": "1",
          "maxCount": "1"
        },
        {
          "id": "https://dcjm.data.vlaanderen.be/ns/financiele-data/taxonomie#DCJMfeit.rubriek",
          "vocabularyLabel": {
            "nl": "rubriek"
          },
          "applicationProfileLabel": {
            "nl": "rubriek"
          },
          "vocabularyDefinition": {
            "nl": "TODO"
          },
          "applicationProfileDefinition": {
            "nl": "TODO"
          },
          "scope": "https://data.vlaanderen.be/id/concept/scope/InPackage",
          "domain": "https://dcjm.data.vlaanderen.be/ns/financiele-data/taxonomie#DCJMfeit",
          "range": {
            "id": "http://www.w3.org/ns/adms#Identifier",
            "vocabularyLabel": {
              "nl": "Identificator"
            },
            "applicationProfileLabel": {
              "nl": "Identificator"
            }
          },
          "minCount": "1",
          "maxCount": "1"
        },
        {
          "id": "https://dcjm.data.vlaanderen.be/ns/financiele-data/taxonomie#DCJMfeit.waarde",
          "vocabularyLabel": {
            "nl": "waarde"
          },
          "applicationProfileLabel": {
            "nl": "waarde"
          },
          "vocabularyDefinition": {
            "nl": "TODO"
          },
          "applicationProfileDefinition": {
            "nl": "TODO"
          },
          "scope": "https://data.vlaanderen.be/id/concept/scope/InPackage",
          "domain": "https://dcjm.data.vlaanderen.be/ns/financiele-data/taxonomie#DCJMfeit",
          "range": {
            "id": "https://schema.org/MonetaryAmount",
            "vocabularyLabel": {
              "nl": "MonetairDatatype"
            },
            "applicationProfileLabel": {
              "nl": "MonetairDatatype"
            }
          },
          "minCount": "1",
          "maxCount": "1"
        }
      ]
    },
    {
      "id": "https://dcjm.data.vlaanderen.be/ns/financiele-data/taxonomie#Code7005",
      "vocabularyLabel": {
        "nl": "Donatie met tegenprestatie"
      },
      "applicationProfileLabel": {
        "nl": "Donatie met tegenprestatie"
      },
      "vocabularyDefinition": {
        "nl": "NOTE"
      },
      "applicationProfileDefinition": {
        "nl": "NOTE"
      },
      "parents": [
        {
          "id": "https://dcjm.data.vlaanderen.be/ns/financiele-data/taxonomie#Code700",
          "vocabularyLabel": {
            "nl": "Inkomgelden en vergoedingen uit eigen activiteiten"
          },
          "applicationProfileLabel": {
            "nl": "Inkomgelden en vergoedingen uit eigen activiteiten"
          }
        }
      ],
      "scope": "https://data.vlaanderen.be/id/concept/scope/InPackage",
      "properties": [
        {
          "id": "https://dcjm.data.vlaanderen.be/ns/financiele-data/taxonomie#Code7005.rubriek",
          "vocabularyLabel": {
            "nl": "rubriek"
          },
          "applicationProfileLabel": {
            "nl": "rubriek"
          },
          "vocabularyDefinition": {
            "nl": "TODO"
          },
          "applicationProfileDefinition": {
            "nl": "TODO"
          },
          "vocabularyUsageNote": {
            "nl": "Default waarde voor dit type Feit is \"7005\"."
          },
          "applicationProfileUsageNote": {
            "nl": "Default waarde voor dit type Feit is \"7005\"."
          },
          "scope": "https://data.vlaanderen.be/id/concept/scope/InPackage",
          "domain": "https://dcjm.data.vlaanderen.be/ns/financiele-data/taxonomie#Code7005",
          "range": {
            "id": "http://www.w3.org/ns/adms#Identifier",
            "vocabularyLabel": {
              "nl": "Identificator"
            },
            "applicationProfileLabel": {
              "nl": "Identificator"
            }
          },
          "minCount": "1",
          "maxCount": "1"
        }
      ]
    },
    {
      "id": "https://dcjm.data.vlaanderen.be/ns/financiele-data/taxonomie#HuidigePeriode",
      "vocabularyLabel": {
        "nl": "HuidigePeriode"
      },
      "applicationProfileLabel": {
        "nl": "HuidigePeriode"
      },
      "vocabularyDefinition": {
        "nl": "De Context van dit feit."
      },
      "applicationProfileDefinition": {
        "nl": "De Context van dit feit."
      },
      "parents": [
        {
          "id": "https://data.vlaanderen.be/ns/financiele-rapportering#Context",
          "vocabularyLabel": {
            "nl": "Context"
          },
          "applicationProfileLabel": {
            "nl": "Context"
          }
        }
      ],
      "scope": "https://data.vlaanderen.be/id/concept/scope/InPackage",
      "properties": [
        {
          "id": "https://dcjm.data.vlaanderen.be/ns/financiele-data/taxonomie#HuidigePeriode.entiteit",
          "vocabularyLabel": {
            "nl": "entiteit"
          },
          "applicationProfileLabel": {
            "nl": "entiteit"
          },
          "vocabularyDefinition": {
            "nl": "TODO"
          },
          "applicationProfileDefinition": {
            "nl": "TODO"
          },
          "scope": "https://data.vlaanderen.be/id/concept/scope/InPackage",
          "domain": "https://dcjm.data.vlaanderen.be/ns/financiele-data/taxonomie#HuidigePeriode",
          "range": {
            "id": "http://www.w3.org/ns/org#Organization",
            "vocabularyLabel": {
              "nl": "Organisatie"
            },
            "applicationProfileLabel": {
              "nl": "Organisatie"
            }
          },
          "minCount": "1",
          "maxCount": "1"
        },
        {
          "id": "https://dcjm.data.vlaanderen.be/ns/financiele-data/taxonomie#Code70/76AContext.periode",
          "vocabularyLabel": {
            "nl": "periode"
          },
          "applicationProfileLabel": {
            "nl": "periode"
          },
          "vocabularyDefinition": {
            "nl": "TODO"
          },
          "applicationProfileDefinition": {
            "nl": "TODO"
          },
          "scope": "https://data.vlaanderen.be/id/concept/scope/InPackage",
          "domain": "https://dcjm.data.vlaanderen.be/ns/financiele-data/taxonomie#HuidigePeriode",
          "range": {
            "id": "http://def.isotc211.org/iso19108/2006/TemporalObjects#TM_Instant",
            "vocabularyLabel": {
              "nl": "Moment"
            },
            "applicationProfileLabel": {
              "nl": "Moment"
            }
          },
          "minCount": "1",
          "maxCount": "1"
        },
        {
          "id": "https://dcjm.data.vlaanderen.be/ns/financiele-data/taxonomie#HuidigePeriode.rapport",
          "vocabularyLabel": {
            "nl": "rapport"
          },
          "applicationProfileLabel": {
            "nl": "rapport"
          },
          "vocabularyDefinition": {
            "nl": "TODO"
          },
          "applicationProfileDefinition": {
            "nl": "TODO"
          },
          "scope": "https://data.vlaanderen.be/id/concept/scope/InPackage",
          "domain": "https://dcjm.data.vlaanderen.be/ns/financiele-data/taxonomie#HuidigePeriode",
          "range": {
            "id": "https://data.vlaanderen.be/ns/financiele-rapportering#FinancieelRapport",
            "vocabularyLabel": {
              "nl": "FinancieelRapport"
            },
            "applicationProfileLabel": {
              "nl": "FinancieelRapport"
            }
          },
          "minCount": "1",
          "maxCount": "1"
        }
      ]
    },
    {
      "id": "https://dcjm.data.vlaanderen.be/ns/financiele-data/taxonomie#Code700",
      "vocabularyLabel": {
        "nl": "Inkomgelden en vergoedingen uit eigen activiteiten"
      },
      "applicationProfileLabel": {
        "nl": "Inkomgelden en vergoedingen uit eigen activiteiten"
      },
      "vocabularyDefinition": {
        "nl": "NOTE"
      },
      "applicationProfileDefinition": {
        "nl": "NOTE"
      },
      "parents": [
        {
          "id": "https://dcjm.data.vlaanderen.be/ns/financiele-data/taxonomie#Code70",
          "vocabularyLabel": {
            "nl": "Omzet"
          },
          "applicationProfileLabel": {
            "nl": "Omzet"
          }
        }
      ],
      "scope": "https://data.vlaanderen.be/id/concept/scope/InPackage",
      "properties": [
        {
          "id": "https://dcjm.data.vlaanderen.be/ns/financiele-data/taxonomie#Code700.rubriek",
          "vocabularyLabel": {
            "nl": "rubriek"
          },
          "applicationProfileLabel": {
            "nl": "rubriek"
          },
          "vocabularyDefinition": {
            "nl": "TODO"
          },
          "applicationProfileDefinition": {
            "nl": "TODO"
          },
          "vocabularyUsageNote": {
            "nl": "Default waarde voor dit type Feit is \"700\"."
          },
          "applicationProfileUsageNote": {
            "nl": "Default waarde voor dit type Feit is \"700\"."
          },
          "scope": "https://data.vlaanderen.be/id/concept/scope/InPackage",
          "domain": "https://dcjm.data.vlaanderen.be/ns/financiele-data/taxonomie#Code700",
          "range": {
            "id": "http://www.w3.org/ns/adms#Identifier",
            "vocabularyLabel": {
              "nl": "Identificator"
            },
            "applicationProfileLabel": {
              "nl": "Identificator"
            }
          },
          "minCount": "1",
          "maxCount": "1"
        }
      ]
    },
    {
      "id": "https://dcjm.data.vlaanderen.be/ns/financiele-data/taxonomie#Code7001",
      "vocabularyLabel": {
        "nl": "Inschrijvingsgelden en ticketverkoop"
      },
      "applicationProfileLabel": {
        "nl": "Inschrijvingsgelden en ticketverkoop"
      },
      "vocabularyDefinition": {
        "nl": "NOTE"
      },
      "applicationProfileDefinition": {
        "nl": "NOTE"
      },
      "parents": [
        {
          "id": "https://dcjm.data.vlaanderen.be/ns/financiele-data/taxonomie#Code700",
          "vocabularyLabel": {
            "nl": "Inkomgelden en vergoedingen uit eigen activiteiten"
          },
          "applicationProfileLabel": {
            "nl": "Inkomgelden en vergoedingen uit eigen activiteiten"
          }
        }
      ],
      "scope": "https://data.vlaanderen.be/id/concept/scope/InPackage",
      "properties": [
        {
          "id": "https://dcjm.data.vlaanderen.be/ns/financiele-data/taxonomie#Code7001.rubriek",
          "vocabularyLabel": {
            "nl": "rubriek"
          },
          "applicationProfileLabel": {
            "nl": "rubriek"
          },
          "vocabularyDefinition": {
            "nl": "TODO"
          },
          "applicationProfileDefinition": {
            "nl": "TODO"
          },
          "vocabularyUsageNote": {
            "nl": "Default waarde voor dit type Feit is \"7001\"."
          },
          "applicationProfileUsageNote": {
            "nl": "Default waarde voor dit type Feit is \"7001\"."
          },
          "scope": "https://data.vlaanderen.be/id/concept/scope/InPackage",
          "domain": "https://dcjm.data.vlaanderen.be/ns/financiele-data/taxonomie#Code7001",
          "range": {
            "id": "http://www.w3.org/ns/adms#Identifier",
            "vocabularyLabel": {
              "nl": "Identificator"
            },
            "applicationProfileLabel": {
              "nl": "Identificator"
            }
          },
          "minCount": "1",
          "maxCount": "1"
        }
      ]
    },
    {
      "id": "https://dcjm.data.vlaanderen.be/ns/financiele-data/taxonomie#Code70",
      "vocabularyLabel": {
        "nl": "Omzet"
      },
      "applicationProfileLabel": {
        "nl": "Omzet"
      },
      "vocabularyDefinition": {
        "nl": "NOTE"
      },
      "applicationProfileDefinition": {
        "nl": "NOTE"
      },
      "parents": [
        {
          "id": "https://dcjm.data.vlaanderen.be/ns/financiele-data/taxonomie#Code70/76A",
          "vocabularyLabel": {
            "nl": "Bedrijfsopbrengsten"
          },
          "applicationProfileLabel": {
            "nl": "Bedrijfsopbrengsten"
          }
        }
      ],
      "scope": "https://data.vlaanderen.be/id/concept/scope/InPackage",
      "properties": [
        {
          "id": "https://dcjm.data.vlaanderen.be/ns/financiele-data/taxonomie#Code70.rubriek",
          "vocabularyLabel": {
            "nl": "rubriek"
          },
          "applicationProfileLabel": {
            "nl": "rubriek"
          },
          "vocabularyDefinition": {
            "nl": "TODO"
          },
          "applicationProfileDefinition": {
            "nl": "TODO"
          },
          "vocabularyUsageNote": {
            "nl": "Default waarde voor dit type Feit is \"70\"."
          },
          "applicationProfileUsageNote": {
            "nl": "Default waarde voor dit type Feit is \"70\"."
          },
          "scope": "https://data.vlaanderen.be/id/concept/scope/InPackage",
          "domain": "https://dcjm.data.vlaanderen.be/ns/financiele-data/taxonomie#Code70",
          "range": {
            "id": "http://www.w3.org/ns/adms#Identifier",
            "vocabularyLabel": {
              "nl": "Identificator"
            },
            "applicationProfileLabel": {
              "nl": "Identificator"
            }
          },
          "minCount": "1",
          "maxCount": "1"
        }
      ]
    },
    {
      "id": "https://dcjm.data.vlaanderen.be/ns/financiele-data/taxonomie#Code7008",
      "vocabularyLabel": {
        "nl": "Overige vergoedingen"
      },
      "applicationProfileLabel": {
        "nl": "Overige vergoedingen"
      },
      "vocabularyDefinition": {
        "nl": "Deze rubriek bevat alle opbrengsten die tot de omzet behoren en die voortvloeien uit Inkomgelden en vergoedingen uit eigen activiteiten van de VZW, IVZW of Stichting, maar die niet in één van de andere beschikbare rubrieken kunnen worden ondergebracht."
      },
      "applicationProfileDefinition": {
        "nl": "Deze rubriek bevat alle opbrengsten die tot de omzet behoren en die voortvloeien uit Inkomgelden en vergoedingen uit eigen activiteiten van de VZW, IVZW of Stichting, maar die niet in één van de andere beschikbare rubrieken kunnen worden ondergebracht."
      },
      "parents": [
        {
          "id": "https://dcjm.data.vlaanderen.be/ns/financiele-data/taxonomie#Code700",
          "vocabularyLabel": {
            "nl": "Inkomgelden en vergoedingen uit eigen activiteiten"
          },
          "applicationProfileLabel": {
            "nl": "Inkomgelden en vergoedingen uit eigen activiteiten"
          }
        }
      ],
      "scope": "https://data.vlaanderen.be/id/concept/scope/InPackage",
      "properties": [
        {
          "id": "https://dcjm.data.vlaanderen.be/ns/financiele-data/taxonomie#Code7008.rubriek",
          "vocabularyLabel": {
            "nl": "rubriek"
          },
          "applicationProfileLabel": {
            "nl": "rubriek"
          },
          "vocabularyDefinition": {
            "nl": "TODO"
          },
          "applicationProfileDefinition": {
            "nl": "TODO"
          },
          "vocabularyUsageNote": {
            "nl": "Default waarde voor dit type Feit is \"7008\"."
          },
          "applicationProfileUsageNote": {
            "nl": "Default waarde voor dit type Feit is \"7008\"."
          },
          "scope": "https://data.vlaanderen.be/id/concept/scope/InPackage",
          "domain": "https://dcjm.data.vlaanderen.be/ns/financiele-data/taxonomie#Code7008",
          "range": {
            "id": "http://www.w3.org/ns/adms#Identifier",
            "vocabularyLabel": {
              "nl": "Identificator"
            },
            "applicationProfileLabel": {
              "nl": "Identificator"
            }
          },
          "minCount": "1",
          "maxCount": "1"
        }
      ]
    }
  ],
  "inPackageClasses": [
    {
      "id": "https://dcjm.data.vlaanderen.be/ns/financiele-data/taxonomie#Code70/76A",
      "vocabularyLabel": {
        "nl": "Bedrijfsopbrengsten"
      },
      "applicationProfileLabel": {
        "nl": "Bedrijfsopbrengsten"
      },
      "vocabularyDefinition": {
        "nl": "Onder de bedrijfsopbrengsten wordt verstaan de opbrengsten die voortvloeien uit de normale exploitatie of uitbating van de organisatie."
      },
      "applicationProfileDefinition": {
        "nl": "Onder de bedrijfsopbrengsten wordt verstaan de opbrengsten die voortvloeien uit de normale exploitatie of uitbating van de organisatie."
      },
      "parents": [
        {
          "id": "https://dcjm.data.vlaanderen.be/ns/financiele-data/taxonomie#DCJMfeit",
          "vocabularyLabel": {
            "nl": "DCJMfeit"
          },
          "applicationProfileLabel": {
            "nl": "DCJMfeit"
          }
        }
      ],
      "scope": "https://data.vlaanderen.be/id/concept/scope/InPackage",
      "properties": [
        {
          "id": "https://dcjm.data.vlaanderen.be/ns/financiele-data/taxonomie#Bedrijfsopbrengsten.balanstype",
          "vocabularyLabel": {
            "nl": "balanstype"
          },
          "applicationProfileLabel": {
            "nl": "balanstype"
          },
          "vocabularyDefinition": {
            "nl": "TODO"
          },
          "applicationProfileDefinition": {
            "nl": "TODO"
          },
          "vocabularyUsageNote": {
            "nl": "Default waarde voor dit type Feit is \"krediet\"."
          },
          "applicationProfileUsageNote": {
            "nl": "Default waarde voor dit type Feit is \"krediet\"."
          },
          "scope": "https://data.vlaanderen.be/id/concept/scope/InPackage",
          "domain": "https://dcjm.data.vlaanderen.be/ns/financiele-data/taxonomie#Code70/76A",
          "range": {
            "id": "http://www.w3.org/2004/02/skos/core#Concept",
            "vocabularyLabel": {
              "nl": "BalansType"
            },
            "applicationProfileLabel": {
              "nl": "BalansType"
            }
          },
          "minCount": "1",
          "maxCount": "1"
        },
        {
          "id": "https://dcjm.data.vlaanderen.be/ns/financiele-data/taxonomie#rubriek",
          "vocabularyLabel": {
            "nl": "rubriek"
          },
          "applicationProfileLabel": {
            "nl": "rubriek"
          },
          "vocabularyDefinition": {
            "nl": "TODO"
          },
          "applicationProfileDefinition": {
            "nl": "TODO"
          },
          "vocabularyUsageNote": {
            "nl": "Default waarde voor dit type Feit is \"70/76A\"."
          },
          "applicationProfileUsageNote": {
            "nl": "Default waarde voor dit type Feit is \"70/76A\"."
          },
          "scope": "https://data.vlaanderen.be/id/concept/scope/InPackage",
          "domain": "https://dcjm.data.vlaanderen.be/ns/financiele-data/taxonomie#Code70/76A",
          "range": {
            "id": "http://www.w3.org/ns/adms#Identifier",
            "vocabularyLabel": {
              "nl": "Identificator"
            },
            "applicationProfileLabel": {
              "nl": "Identificator"
            }
          },
          "minCount": "1",
          "maxCount": "1"
        }
      ]
    },
    {
      "id": "https://dcjm.data.vlaanderen.be/ns/financiele-data/taxonomie#DCJMfeit",
      "vocabularyLabel": {
        "nl": "DCJMfeit"
      },
      "applicationProfileLabel": {
        "nl": "DCJMfeit"
      },
      "vocabularyDefinition": {
        "nl": "TODO"
      },
      "applicationProfileDefinition": {
        "nl": "TODO"
      },
      "parents": [
        {
          "id": "https://data.vlaanderen.be/ns/financiele-rapportering#Feit",
          "vocabularyLabel": {
            "nl": "Feit"
          },
          "applicationProfileLabel": {
            "nl": "Feit"
          }
        }
      ],
      "scope": "https://data.vlaanderen.be/id/concept/scope/InPackage",
      "properties": [
        {
          "id": "https://dcjm.data.vlaanderen.be/ns/financiele-data/taxonomie#DCJMfeit.balanstype",
          "vocabularyLabel": {
            "nl": "balanstype"
          },
          "applicationProfileLabel": {
            "nl": "balanstype"
          },
          "vocabularyDefinition": {
            "nl": "TODO"
          },
          "applicationProfileDefinition": {
            "nl": "TODO"
          },
          "scope": "https://data.vlaanderen.be/id/concept/scope/InPackage",
          "domain": "https://dcjm.data.vlaanderen.be/ns/financiele-data/taxonomie#DCJMfeit",
          "range": {
            "id": "http://www.w3.org/2004/02/skos/core#Concept",
            "vocabularyLabel": {
              "nl": "BalansType"
            },
            "applicationProfileLabel": {
              "nl": "BalansType"
            }
          },
          "minCount": "1",
          "maxCount": "1"
        },
        {
          "id": "https://dcjm.data.vlaanderen.be/ns/financiele-data/taxonomie#DCJMfeit.concept",
          "vocabularyLabel": {
            "nl": "concept"
          },
          "applicationProfileLabel": {
            "nl": "concept"
          },
          "vocabularyDefinition": {
            "nl": "TODO"
          },
          "applicationProfileDefinition": {
            "nl": "TODO"
          },
          "scope": "https://data.vlaanderen.be/id/concept/scope/InPackage",
          "domain": "https://dcjm.data.vlaanderen.be/ns/financiele-data/taxonomie#DCJMfeit",
          "range": {
            "id": "https://data.vlaanderen.be/ns/financiele-rapportering#Concept",
            "vocabularyLabel": {
              "nl": "Concept"
            },
            "applicationProfileLabel": {
              "nl": "Concept"
            }
          },
          "minCount": "0",
          "maxCount": "1"
        },
        {
          "id": "https://dcjm.data.vlaanderen.be/ns/financiele-data/taxonomie#context",
          "vocabularyLabel": {
            "nl": "context"
          },
          "applicationProfileLabel": {
            "nl": "context"
          },
          "vocabularyDefinition": {
            "nl": "TODO"
          },
          "applicationProfileDefinition": {
            "nl": "TODO"
          },
          "scope": "https://data.vlaanderen.be/id/concept/scope/InPackage",
          "domain": "https://dcjm.data.vlaanderen.be/ns/financiele-data/taxonomie#DCJMfeit",
          "range": {
            "id": "https://dcjm.data.vlaanderen.be/ns/financiele-data/taxonomie#HuidigePeriode",
            "vocabularyLabel": {
              "nl": "HuidigePeriode"
            },
            "applicationProfileLabel": {
              "nl": "HuidigePeriode"
            }
          }
        },
        {
          "id": "https://dcjm.data.vlaanderen.be/ns/financiele-data/taxonomie#orde",
          "vocabularyLabel": {
            "nl": "orde"
          },
          "applicationProfileLabel": {
            "nl": "orde"
          },
          "vocabularyDefinition": {
            "nl": "TODO"
          },
          "applicationProfileDefinition": {
            "nl": "TODO"
          },
          "scope": "https://data.vlaanderen.be/id/concept/scope/InPackage",
          "domain": "https://dcjm.data.vlaanderen.be/ns/financiele-data/taxonomie#DCJMfeit",
          "range": {
            "id": "http://www.w3.org/2001/XMLSchema#integer",
            "vocabularyLabel": {
              "nl": "Integer"
            },
            "applicationProfileLabel": {
              "nl": "Integer"
            }
          },
          "minCount": "0",
          "maxCount": "1"
        },
        {
          "id": "https://dcjm.data.vlaanderen.be/ns/financiele-data/taxonomie#DCJMfeit.rapport",
          "vocabularyLabel": {
            "nl": "rapport"
          },
          "applicationProfileLabel": {
            "nl": "rapport"
          },
          "vocabularyDefinition": {
            "nl": "TODO"
          },
          "applicationProfileDefinition": {
            "nl": "TODO"
          },
          "scope": "https://data.vlaanderen.be/id/concept/scope/InPackage",
          "domain": "https://dcjm.data.vlaanderen.be/ns/financiele-data/taxonomie#DCJMfeit",
          "range": {
            "id": "https://data.vlaanderen.be/ns/financiele-rapportering#FinancieelRapport",
            "vocabularyLabel": {
              "nl": "FinancieelRapport"
            },
            "applicationProfileLabel": {
              "nl": "FinancieelRapport"
            }
          },
          "minCount": "1",
          "maxCount": "1"
        },
        {
          "id": "https://dcjm.data.vlaanderen.be/ns/financiele-data/taxonomie#DCJMfeit.rubriek",
          "vocabularyLabel": {
            "nl": "rubriek"
          },
          "applicationProfileLabel": {
            "nl": "rubriek"
          },
          "vocabularyDefinition": {
            "nl": "TODO"
          },
          "applicationProfileDefinition": {
            "nl": "TODO"
          },
          "scope": "https://data.vlaanderen.be/id/concept/scope/InPackage",
          "domain": "https://dcjm.data.vlaanderen.be/ns/financiele-data/taxonomie#DCJMfeit",
          "range": {
            "id": "http://www.w3.org/ns/adms#Identifier",
            "vocabularyLabel": {
              "nl": "Identificator"
            },
            "applicationProfileLabel": {
              "nl": "Identificator"
            }
          },
          "minCount": "1",
          "maxCount": "1"
        },
        {
          "id": "https://dcjm.data.vlaanderen.be/ns/financiele-data/taxonomie#DCJMfeit.waarde",
          "vocabularyLabel": {
            "nl": "waarde"
          },
          "applicationProfileLabel": {
            "nl": "waarde"
          },
          "vocabularyDefinition": {
            "nl": "TODO"
          },
          "applicationProfileDefinition": {
            "nl": "TODO"
          },
          "scope": "https://data.vlaanderen.be/id/concept/scope/InPackage",
          "domain": "https://dcjm.data.vlaanderen.be/ns/financiele-data/taxonomie#DCJMfeit",
          "range": {
            "id": "https://schema.org/MonetaryAmount",
            "vocabularyLabel": {
              "nl": "MonetairDatatype"
            },
            "applicationProfileLabel": {
              "nl": "MonetairDatatype"
            }
          },
          "minCount": "1",
          "maxCount": "1"
        }
      ]
    },
    {
      "id": "https://dcjm.data.vlaanderen.be/ns/financiele-data/taxonomie#Code7005",
      "vocabularyLabel": {
        "nl": "Donatie met tegenprestatie"
      },
      "applicationProfileLabel": {
        "nl": "Donatie met tegenprestatie"
      },
      "vocabularyDefinition": {
        "nl": "NOTE"
      },
      "applicationProfileDefinition": {
        "nl": "NOTE"
      },
      "parents": [
        {
          "id": "https://dcjm.data.vlaanderen.be/ns/financiele-data/taxonomie#Code700",
          "vocabularyLabel": {
            "nl": "Inkomgelden en vergoedingen uit eigen activiteiten"
          },
          "applicationProfileLabel": {
            "nl": "Inkomgelden en vergoedingen uit eigen activiteiten"
          }
        }
      ],
      "scope": "https://data.vlaanderen.be/id/concept/scope/InPackage",
      "properties": [
        {
          "id": "https://dcjm.data.vlaanderen.be/ns/financiele-data/taxonomie#Code7005.rubriek",
          "vocabularyLabel": {
            "nl": "rubriek"
          },
          "applicationProfileLabel": {
            "nl": "rubriek"
          },
          "vocabularyDefinition": {
            "nl": "TODO"
          },
          "applicationProfileDefinition": {
            "nl": "TODO"
          },
          "vocabularyUsageNote": {
            "nl": "Default waarde voor dit type Feit is \"7005\"."
          },
          "applicationProfileUsageNote": {
            "nl": "Default waarde voor dit type Feit is \"7005\"."
          },
          "scope": "https://data.vlaanderen.be/id/concept/scope/InPackage",
          "domain": "https://dcjm.data.vlaanderen.be/ns/financiele-data/taxonomie#Code7005",
          "range": {
            "id": "http://www.w3.org/ns/adms#Identifier",
            "vocabularyLabel": {
              "nl": "Identificator"
            },
            "applicationProfileLabel": {
              "nl": "Identificator"
            }
          },
          "minCount": "1",
          "maxCount": "1"
        }
      ]
    },
    {
      "id": "https://dcjm.data.vlaanderen.be/ns/financiele-data/taxonomie#HuidigePeriode",
      "vocabularyLabel": {
        "nl": "HuidigePeriode"
      },
      "applicationProfileLabel": {
        "nl": "HuidigePeriode"
      },
      "vocabularyDefinition": {
        "nl": "De Context van dit feit."
      },
      "applicationProfileDefinition": {
        "nl": "De Context van dit feit."
      },
      "parents": [
        {
          "id": "https://data.vlaanderen.be/ns/financiele-rapportering#Context",
          "vocabularyLabel": {
            "nl": "Context"
          },
          "applicationProfileLabel": {
            "nl": "Context"
          }
        }
      ],
      "scope": "https://data.vlaanderen.be/id/concept/scope/InPackage",
      "properties": [
        {
          "id": "https://dcjm.data.vlaanderen.be/ns/financiele-data/taxonomie#HuidigePeriode.entiteit",
          "vocabularyLabel": {
            "nl": "entiteit"
          },
          "applicationProfileLabel": {
            "nl": "entiteit"
          },
          "vocabularyDefinition": {
            "nl": "TODO"
          },
          "applicationProfileDefinition": {
            "nl": "TODO"
          },
          "scope": "https://data.vlaanderen.be/id/concept/scope/InPackage",
          "domain": "https://dcjm.data.vlaanderen.be/ns/financiele-data/taxonomie#HuidigePeriode",
          "range": {
            "id": "http://www.w3.org/ns/org#Organization",
            "vocabularyLabel": {
              "nl": "Organisatie"
            },
            "applicationProfileLabel": {
              "nl": "Organisatie"
            }
          },
          "minCount": "1",
          "maxCount": "1"
        },
        {
          "id": "https://dcjm.data.vlaanderen.be/ns/financiele-data/taxonomie#Code70/76AContext.periode",
          "vocabularyLabel": {
            "nl": "periode"
          },
          "applicationProfileLabel": {
            "nl": "periode"
          },
          "vocabularyDefinition": {
            "nl": "TODO"
          },
          "applicationProfileDefinition": {
            "nl": "TODO"
          },
          "scope": "https://data.vlaanderen.be/id/concept/scope/InPackage",
          "domain": "https://dcjm.data.vlaanderen.be/ns/financiele-data/taxonomie#HuidigePeriode",
          "range": {
            "id": "http://def.isotc211.org/iso19108/2006/TemporalObjects#TM_Instant",
            "vocabularyLabel": {
              "nl": "Moment"
            },
            "applicationProfileLabel": {
              "nl": "Moment"
            }
          },
          "minCount": "1",
          "maxCount": "1"
        },
        {
          "id": "https://dcjm.data.vlaanderen.be/ns/financiele-data/taxonomie#HuidigePeriode.rapport",
          "vocabularyLabel": {
            "nl": "rapport"
          },
          "applicationProfileLabel": {
            "nl": "rapport"
          },
          "vocabularyDefinition": {
            "nl": "TODO"
          },
          "applicationProfileDefinition": {
            "nl": "TODO"
          },
          "scope": "https://data.vlaanderen.be/id/concept/scope/InPackage",
          "domain": "https://dcjm.data.vlaanderen.be/ns/financiele-data/taxonomie#HuidigePeriode",
          "range": {
            "id": "https://data.vlaanderen.be/ns/financiele-rapportering#FinancieelRapport",
            "vocabularyLabel": {
              "nl": "FinancieelRapport"
            },
            "applicationProfileLabel": {
              "nl": "FinancieelRapport"
            }
          },
          "minCount": "1",
          "maxCount": "1"
        }
      ]
    },
    {
      "id": "https://dcjm.data.vlaanderen.be/ns/financiele-data/taxonomie#Code700",
      "vocabularyLabel": {
        "nl": "Inkomgelden en vergoedingen uit eigen activiteiten"
      },
      "applicationProfileLabel": {
        "nl": "Inkomgelden en vergoedingen uit eigen activiteiten"
      },
      "vocabularyDefinition": {
        "nl": "NOTE"
      },
      "applicationProfileDefinition": {
        "nl": "NOTE"
      },
      "parents": [
        {
          "id": "https://dcjm.data.vlaanderen.be/ns/financiele-data/taxonomie#Code70",
          "vocabularyLabel": {
            "nl": "Omzet"
          },
          "applicationProfileLabel": {
            "nl": "Omzet"
          }
        }
      ],
      "scope": "https://data.vlaanderen.be/id/concept/scope/InPackage",
      "properties": [
        {
          "id": "https://dcjm.data.vlaanderen.be/ns/financiele-data/taxonomie#Code700.rubriek",
          "vocabularyLabel": {
            "nl": "rubriek"
          },
          "applicationProfileLabel": {
            "nl": "rubriek"
          },
          "vocabularyDefinition": {
            "nl": "TODO"
          },
          "applicationProfileDefinition": {
            "nl": "TODO"
          },
          "vocabularyUsageNote": {
            "nl": "Default waarde voor dit type Feit is \"700\"."
          },
          "applicationProfileUsageNote": {
            "nl": "Default waarde voor dit type Feit is \"700\"."
          },
          "scope": "https://data.vlaanderen.be/id/concept/scope/InPackage",
          "domain": "https://dcjm.data.vlaanderen.be/ns/financiele-data/taxonomie#Code700",
          "range": {
            "id": "http://www.w3.org/ns/adms#Identifier",
            "vocabularyLabel": {
              "nl": "Identificator"
            },
            "applicationProfileLabel": {
              "nl": "Identificator"
            }
          },
          "minCount": "1",
          "maxCount": "1"
        }
      ]
    },
    {
      "id": "https://dcjm.data.vlaanderen.be/ns/financiele-data/taxonomie#Code7001",
      "vocabularyLabel": {
        "nl": "Inschrijvingsgelden en ticketverkoop"
      },
      "applicationProfileLabel": {
        "nl": "Inschrijvingsgelden en ticketverkoop"
      },
      "vocabularyDefinition": {
        "nl": "NOTE"
      },
      "applicationProfileDefinition": {
        "nl": "NOTE"
      },
      "parents": [
        {
          "id": "https://dcjm.data.vlaanderen.be/ns/financiele-data/taxonomie#Code700",
          "vocabularyLabel": {
            "nl": "Inkomgelden en vergoedingen uit eigen activiteiten"
          },
          "applicationProfileLabel": {
            "nl": "Inkomgelden en vergoedingen uit eigen activiteiten"
          }
        }
      ],
      "scope": "https://data.vlaanderen.be/id/concept/scope/InPackage",
      "properties": [
        {
          "id": "https://dcjm.data.vlaanderen.be/ns/financiele-data/taxonomie#Code7001.rubriek",
          "vocabularyLabel": {
            "nl": "rubriek"
          },
          "applicationProfileLabel": {
            "nl": "rubriek"
          },
          "vocabularyDefinition": {
            "nl": "TODO"
          },
          "applicationProfileDefinition": {
            "nl": "TODO"
          },
          "vocabularyUsageNote": {
            "nl": "Default waarde voor dit type Feit is \"7001\"."
          },
          "applicationProfileUsageNote": {
            "nl": "Default waarde voor dit type Feit is \"7001\"."
          },
          "scope": "https://data.vlaanderen.be/id/concept/scope/InPackage",
          "domain": "https://dcjm.data.vlaanderen.be/ns/financiele-data/taxonomie#Code7001",
          "range": {
            "id": "http://www.w3.org/ns/adms#Identifier",
            "vocabularyLabel": {
              "nl": "Identificator"
            },
            "applicationProfileLabel": {
              "nl": "Identificator"
            }
          },
          "minCount": "1",
          "maxCount": "1"
        }
      ]
    },
    {
      "id": "https://dcjm.data.vlaanderen.be/ns/financiele-data/taxonomie#Code70",
      "vocabularyLabel": {
        "nl": "Omzet"
      },
      "applicationProfileLabel": {
        "nl": "Omzet"
      },
      "vocabularyDefinition": {
        "nl": "NOTE"
      },
      "applicationProfileDefinition": {
        "nl": "NOTE"
      },
      "parents": [
        {
          "id": "https://dcjm.data.vlaanderen.be/ns/financiele-data/taxonomie#Code70/76A",
          "vocabularyLabel": {
            "nl": "Bedrijfsopbrengsten"
          },
          "applicationProfileLabel": {
            "nl": "Bedrijfsopbrengsten"
          }
        }
      ],
      "scope": "https://data.vlaanderen.be/id/concept/scope/InPackage",
      "properties": [
        {
          "id": "https://dcjm.data.vlaanderen.be/ns/financiele-data/taxonomie#Code70.rubriek",
          "vocabularyLabel": {
            "nl": "rubriek"
          },
          "applicationProfileLabel": {
            "nl": "rubriek"
          },
          "vocabularyDefinition": {
            "nl": "TODO"
          },
          "applicationProfileDefinition": {
            "nl": "TODO"
          },
          "vocabularyUsageNote": {
            "nl": "Default waarde voor dit type Feit is \"70\"."
          },
          "applicationProfileUsageNote": {
            "nl": "Default waarde voor dit type Feit is \"70\"."
          },
          "scope": "https://data.vlaanderen.be/id/concept/scope/InPackage",
          "domain": "https://dcjm.data.vlaanderen.be/ns/financiele-data/taxonomie#Code70",
          "range": {
            "id": "http://www.w3.org/ns/adms#Identifier",
            "vocabularyLabel": {
              "nl": "Identificator"
            },
            "applicationProfileLabel": {
              "nl": "Identificator"
            }
          },
          "minCount": "1",
          "maxCount": "1"
        }
      ]
    },
    {
      "id": "https://dcjm.data.vlaanderen.be/ns/financiele-data/taxonomie#Code7008",
      "vocabularyLabel": {
        "nl": "Overige vergoedingen"
      },
      "applicationProfileLabel": {
        "nl": "Overige vergoedingen"
      },
      "vocabularyDefinition": {
        "nl": "Deze rubriek bevat alle opbrengsten die tot de omzet behoren en die voortvloeien uit Inkomgelden en vergoedingen uit eigen activiteiten van de VZW, IVZW of Stichting, maar die niet in één van de andere beschikbare rubrieken kunnen worden ondergebracht."
      },
      "applicationProfileDefinition": {
        "nl": "Deze rubriek bevat alle opbrengsten die tot de omzet behoren en die voortvloeien uit Inkomgelden en vergoedingen uit eigen activiteiten van de VZW, IVZW of Stichting, maar die niet in één van de andere beschikbare rubrieken kunnen worden ondergebracht."
      },
      "parents": [
        {
          "id": "https://dcjm.data.vlaanderen.be/ns/financiele-data/taxonomie#Code700",
          "vocabularyLabel": {
            "nl": "Inkomgelden en vergoedingen uit eigen activiteiten"
          },
          "applicationProfileLabel": {
            "nl": "Inkomgelden en vergoedingen uit eigen activiteiten"
          }
        }
      ],
      "scope": "https://data.vlaanderen.be/id/concept/scope/InPackage",
      "properties": [
        {
          "id": "https://dcjm.data.vlaanderen.be/ns/financiele-data/taxonomie#Code7008.rubriek",
          "vocabularyLabel": {
            "nl": "rubriek"
          },
          "applicationProfileLabel": {
            "nl": "rubriek"
          },
          "vocabularyDefinition": {
            "nl": "TODO"
          },
          "applicationProfileDefinition": {
            "nl": "TODO"
          },
          "vocabularyUsageNote": {
            "nl": "Default waarde voor dit type Feit is \"7008\"."
          },
          "applicationProfileUsageNote": {
            "nl": "Default waarde voor dit type Feit is \"7008\"."
          },
          "scope": "https://data.vlaanderen.be/id/concept/scope/InPackage",
          "domain": "https://dcjm.data.vlaanderen.be/ns/financiele-data/taxonomie#Code7008",
          "range": {
            "id": "http://www.w3.org/ns/adms#Identifier",
            "vocabularyLabel": {
              "nl": "Identificator"
            },
            "applicationProfileLabel": {
              "nl": "Identificator"
            }
          },
          "minCount": "1",
          "maxCount": "1"
        }
      ]
    }
  ],
  "inPackageDataTypes": [],
  "scopedDataTypes": [],
  "externalProperties": [],
  "inPackageProperties": [
    {
      "id": "https://dcjm.data.vlaanderen.be/ns/financiele-data/taxonomie#Bedrijfsopbrengsten.balanstype",
      "vocabularyLabel": {
        "nl": "balanstype"
      },
      "applicationProfileLabel": {
        "nl": "balanstype"
      },
      "vocabularyDefinition": {
        "nl": "TODO"
      },
      "applicationProfileDefinition": {
        "nl": "TODO"
      },
      "vocabularyUsageNote": {
        "nl": "Default waarde voor dit type Feit is \"krediet\"."
      },
      "applicationProfileUsageNote": {
        "nl": "Default waarde voor dit type Feit is \"krediet\"."
      },
      "scope": "https://data.vlaanderen.be/id/concept/scope/InPackage",
      "domain": "https://dcjm.data.vlaanderen.be/ns/financiele-data/taxonomie#Code70/76A",
      "range": {
        "id": "http://www.w3.org/2004/02/skos/core#Concept",
        "vocabularyLabel": {
          "nl": "BalansType"
        },
        "applicationProfileLabel": {
          "nl": "BalansType"
        }
      },
      "minCount": "1",
      "maxCount": "1"
    },
    {
      "id": "https://dcjm.data.vlaanderen.be/ns/financiele-data/taxonomie#DCJMfeit.balanstype",
      "vocabularyLabel": {
        "nl": "balanstype"
      },
      "applicationProfileLabel": {
        "nl": "balanstype"
      },
      "vocabularyDefinition": {
        "nl": "TODO"
      },
      "applicationProfileDefinition": {
        "nl": "TODO"
      },
      "scope": "https://data.vlaanderen.be/id/concept/scope/InPackage",
      "domain": "https://dcjm.data.vlaanderen.be/ns/financiele-data/taxonomie#DCJMfeit",
      "range": {
        "id": "http://www.w3.org/2004/02/skos/core#Concept",
        "vocabularyLabel": {
          "nl": "BalansType"
        },
        "applicationProfileLabel": {
          "nl": "BalansType"
        }
      },
      "minCount": "1",
      "maxCount": "1"
    },
    {
      "id": "https://dcjm.data.vlaanderen.be/ns/financiele-data/taxonomie#DCJMfeit.concept",
      "vocabularyLabel": {
        "nl": "concept"
      },
      "applicationProfileLabel": {
        "nl": "concept"
      },
      "vocabularyDefinition": {
        "nl": "TODO"
      },
      "applicationProfileDefinition": {
        "nl": "TODO"
      },
      "scope": "https://data.vlaanderen.be/id/concept/scope/InPackage",
      "domain": "https://dcjm.data.vlaanderen.be/ns/financiele-data/taxonomie#DCJMfeit",
      "range": {
        "id": "https://data.vlaanderen.be/ns/financiele-rapportering#Concept",
        "vocabularyLabel": {
          "nl": "Concept"
        },
        "applicationProfileLabel": {
          "nl": "Concept"
        }
      },
      "minCount": "0",
      "maxCount": "1"
    },
    {
      "id": "https://dcjm.data.vlaanderen.be/ns/financiele-data/taxonomie#context",
      "vocabularyLabel": {
        "nl": "context"
      },
      "applicationProfileLabel": {
        "nl": "context"
      },
      "vocabularyDefinition": {
        "nl": "TODO"
      },
      "applicationProfileDefinition": {
        "nl": "TODO"
      },
      "scope": "https://data.vlaanderen.be/id/concept/scope/InPackage",
      "domain": "https://dcjm.data.vlaanderen.be/ns/financiele-data/taxonomie#DCJMfeit",
      "range": {
        "id": "https://dcjm.data.vlaanderen.be/ns/financiele-data/taxonomie#HuidigePeriode",
        "vocabularyLabel": {
          "nl": "HuidigePeriode"
        },
        "applicationProfileLabel": {
          "nl": "HuidigePeriode"
        }
      }
    },
    {
      "id": "https://dcjm.data.vlaanderen.be/ns/financiele-data/taxonomie#HuidigePeriode.entiteit",
      "vocabularyLabel": {
        "nl": "entiteit"
      },
      "applicationProfileLabel": {
        "nl": "entiteit"
      },
      "vocabularyDefinition": {
        "nl": "TODO"
      },
      "applicationProfileDefinition": {
        "nl": "TODO"
      },
      "scope": "https://data.vlaanderen.be/id/concept/scope/InPackage",
      "domain": "https://dcjm.data.vlaanderen.be/ns/financiele-data/taxonomie#HuidigePeriode",
      "range": {
        "id": "http://www.w3.org/ns/org#Organization",
        "vocabularyLabel": {
          "nl": "Organisatie"
        },
        "applicationProfileLabel": {
          "nl": "Organisatie"
        }
      },
      "minCount": "1",
      "maxCount": "1"
    },
    {
      "id": "https://dcjm.data.vlaanderen.be/ns/financiele-data/taxonomie#orde",
      "vocabularyLabel": {
        "nl": "orde"
      },
      "applicationProfileLabel": {
        "nl": "orde"
      },
      "vocabularyDefinition": {
        "nl": "TODO"
      },
      "applicationProfileDefinition": {
        "nl": "TODO"
      },
      "scope": "https://data.vlaanderen.be/id/concept/scope/InPackage",
      "domain": "https://dcjm.data.vlaanderen.be/ns/financiele-data/taxonomie#DCJMfeit",
      "range": {
        "id": "http://www.w3.org/2001/XMLSchema#integer",
        "vocabularyLabel": {
          "nl": "Integer"
        },
        "applicationProfileLabel": {
          "nl": "Integer"
        }
      },
      "minCount": "0",
      "maxCount": "1"
    },
    {
      "id": "https://dcjm.data.vlaanderen.be/ns/financiele-data/taxonomie#Code70/76AContext.periode",
      "vocabularyLabel": {
        "nl": "periode"
      },
      "applicationProfileLabel": {
        "nl": "periode"
      },
      "vocabularyDefinition": {
        "nl": "TODO"
      },
      "applicationProfileDefinition": {
        "nl": "TODO"
      },
      "scope": "https://data.vlaanderen.be/id/concept/scope/InPackage",
      "domain": "https://dcjm.data.vlaanderen.be/ns/financiele-data/taxonomie#HuidigePeriode",
      "range": {
        "id": "http://def.isotc211.org/iso19108/2006/TemporalObjects#TM_Instant",
        "vocabularyLabel": {
          "nl": "Moment"
        },
        "applicationProfileLabel": {
          "nl": "Moment"
        }
      },
      "minCount": "1",
      "maxCount": "1"
    },
    {
      "id": "https://dcjm.data.vlaanderen.be/ns/financiele-data/taxonomie#DCJMfeit.rapport",
      "vocabularyLabel": {
        "nl": "rapport"
      },
      "applicationProfileLabel": {
        "nl": "rapport"
      },
      "vocabularyDefinition": {
        "nl": "TODO"
      },
      "applicationProfileDefinition": {
        "nl": "TODO"
      },
      "scope": "https://data.vlaanderen.be/id/concept/scope/InPackage",
      "domain": "https://dcjm.data.vlaanderen.be/ns/financiele-data/taxonomie#DCJMfeit",
      "range": {
        "id": "https://data.vlaanderen.be/ns/financiele-rapportering#FinancieelRapport",
        "vocabularyLabel": {
          "nl": "FinancieelRapport"
        },
        "applicationProfileLabel": {
          "nl": "FinancieelRapport"
        }
      },
      "minCount": "1",
      "maxCount": "1"
    },
    {
      "id": "https://dcjm.data.vlaanderen.be/ns/financiele-data/taxonomie#HuidigePeriode.rapport",
      "vocabularyLabel": {
        "nl": "rapport"
      },
      "applicationProfileLabel": {
        "nl": "rapport"
      },
      "vocabularyDefinition": {
        "nl": "TODO"
      },
      "applicationProfileDefinition": {
        "nl": "TODO"
      },
      "scope": "https://data.vlaanderen.be/id/concept/scope/InPackage",
      "domain": "https://dcjm.data.vlaanderen.be/ns/financiele-data/taxonomie#HuidigePeriode",
      "range": {
        "id": "https://data.vlaanderen.be/ns/financiele-rapportering#FinancieelRapport",
        "vocabularyLabel": {
          "nl": "FinancieelRapport"
        },
        "applicationProfileLabel": {
          "nl": "FinancieelRapport"
        }
      },
      "minCount": "1",
      "maxCount": "1"
    },
    {
      "id": "https://dcjm.data.vlaanderen.be/ns/financiele-data/taxonomie#rubriek",
      "vocabularyLabel": {
        "nl": "rubriek"
      },
      "applicationProfileLabel": {
        "nl": "rubriek"
      },
      "vocabularyDefinition": {
        "nl": "TODO"
      },
      "applicationProfileDefinition": {
        "nl": "TODO"
      },
      "vocabularyUsageNote": {
        "nl": "Default waarde voor dit type Feit is \"70/76A\"."
      },
      "applicationProfileUsageNote": {
        "nl": "Default waarde voor dit type Feit is \"70/76A\"."
      },
      "scope": "https://data.vlaanderen.be/id/concept/scope/InPackage",
      "domain": "https://dcjm.data.vlaanderen.be/ns/financiele-data/taxonomie#Code70/76A",
      "range": {
        "id": "http://www.w3.org/ns/adms#Identifier",
        "vocabularyLabel": {
          "nl": "Identificator"
        },
        "applicationProfileLabel": {
          "nl": "Identificator"
        }
      },
      "minCount": "1",
      "maxCount": "1"
    },
    {
      "id": "https://dcjm.data.vlaanderen.be/ns/financiele-data/taxonomie#DCJMfeit.rubriek",
      "vocabularyLabel": {
        "nl": "rubriek"
      },
      "applicationProfileLabel": {
        "nl": "rubriek"
      },
      "vocabularyDefinition": {
        "nl": "TODO"
      },
      "applicationProfileDefinition": {
        "nl": "TODO"
      },
      "scope": "https://data.vlaanderen.be/id/concept/scope/InPackage",
      "domain": "https://dcjm.data.vlaanderen.be/ns/financiele-data/taxonomie#DCJMfeit",
      "range": {
        "id": "http://www.w3.org/ns/adms#Identifier",
        "vocabularyLabel": {
          "nl": "Identificator"
        },
        "applicationProfileLabel": {
          "nl": "Identificator"
        }
      },
      "minCount": "1",
      "maxCount": "1"
    },
    {
      "id": "https://dcjm.data.vlaanderen.be/ns/financiele-data/taxonomie#Code7005.rubriek",
      "vocabularyLabel": {
        "nl": "rubriek"
      },
      "applicationProfileLabel": {
        "nl": "rubriek"
      },
      "vocabularyDefinition": {
        "nl": "TODO"
      },
      "applicationProfileDefinition": {
        "nl": "TODO"
      },
      "vocabularyUsageNote": {
        "nl": "Default waarde voor dit type Feit is \"7005\"."
      },
      "applicationProfileUsageNote": {
        "nl": "Default waarde voor dit type Feit is \"7005\"."
      },
      "scope": "https://data.vlaanderen.be/id/concept/scope/InPackage",
      "domain": "https://dcjm.data.vlaanderen.be/ns/financiele-data/taxonomie#Code7005",
      "range": {
        "id": "http://www.w3.org/ns/adms#Identifier",
        "vocabularyLabel": {
          "nl": "Identificator"
        },
        "applicationProfileLabel": {
          "nl": "Identificator"
        }
      },
      "minCount": "1",
      "maxCount": "1"
    },
    {
      "id": "https://dcjm.data.vlaanderen.be/ns/financiele-data/taxonomie#Code700.rubriek",
      "vocabularyLabel": {
        "nl": "rubriek"
      },
      "applicationProfileLabel": {
        "nl": "rubriek"
      },
      "vocabularyDefinition": {
        "nl": "TODO"
      },
      "applicationProfileDefinition": {
        "nl": "TODO"
      },
      "vocabularyUsageNote": {
        "nl": "Default waarde voor dit type Feit is \"700\"."
      },
      "applicationProfileUsageNote": {
        "nl": "Default waarde voor dit type Feit is \"700\"."
      },
      "scope": "https://data.vlaanderen.be/id/concept/scope/InPackage",
      "domain": "https://dcjm.data.vlaanderen.be/ns/financiele-data/taxonomie#Code700",
      "range": {
        "id": "http://www.w3.org/ns/adms#Identifier",
        "vocabularyLabel": {
          "nl": "Identificator"
        },
        "applicationProfileLabel": {
          "nl": "Identificator"
        }
      },
      "minCount": "1",
      "maxCount": "1"
    },
    {
      "id": "https://dcjm.data.vlaanderen.be/ns/financiele-data/taxonomie#Code7001.rubriek",
      "vocabularyLabel": {
        "nl": "rubriek"
      },
      "applicationProfileLabel": {
        "nl": "rubriek"
      },
      "vocabularyDefinition": {
        "nl": "TODO"
      },
      "applicationProfileDefinition": {
        "nl": "TODO"
      },
      "vocabularyUsageNote": {
        "nl": "Default waarde voor dit type Feit is \"7001\"."
      },
      "applicationProfileUsageNote": {
        "nl": "Default waarde voor dit type Feit is \"7001\"."
      },
      "scope": "https://data.vlaanderen.be/id/concept/scope/InPackage",
      "domain": "https://dcjm.data.vlaanderen.be/ns/financiele-data/taxonomie#Code7001",
      "range": {
        "id": "http://www.w3.org/ns/adms#Identifier",
        "vocabularyLabel": {
          "nl": "Identificator"
        },
        "applicationProfileLabel": {
          "nl": "Identificator"
        }
      },
      "minCount": "1",
      "maxCount": "1"
    },
    {
      "id": "https://dcjm.data.vlaanderen.be/ns/financiele-data/taxonomie#Code70.rubriek",
      "vocabularyLabel": {
        "nl": "rubriek"
      },
      "applicationProfileLabel": {
        "nl": "rubriek"
      },
      "vocabularyDefinition": {
        "nl": "TODO"
      },
      "applicationProfileDefinition": {
        "nl": "TODO"
      },
      "vocabularyUsageNote": {
        "nl": "Default waarde voor dit type Feit is \"70\"."
      },
      "applicationProfileUsageNote": {
        "nl": "Default waarde voor dit type Feit is \"70\"."
      },
      "scope": "https://data.vlaanderen.be/id/concept/scope/InPackage",
      "domain": "https://dcjm.data.vlaanderen.be/ns/financiele-data/taxonomie#Code70",
      "range": {
        "id": "http://www.w3.org/ns/adms#Identifier",
        "vocabularyLabel": {
          "nl": "Identificator"
        },
        "applicationProfileLabel": {
          "nl": "Identificator"
        }
      },
      "minCount": "1",
      "maxCount": "1"
    },
    {
      "id": "https://dcjm.data.vlaanderen.be/ns/financiele-data/taxonomie#Code7008.rubriek",
      "vocabularyLabel": {
        "nl": "rubriek"
      },
      "applicationProfileLabel": {
        "nl": "rubriek"
      },
      "vocabularyDefinition": {
        "nl": "TODO"
      },
      "applicationProfileDefinition": {
        "nl": "TODO"
      },
      "vocabularyUsageNote": {
        "nl": "Default waarde voor dit type Feit is \"7008\"."
      },
      "applicationProfileUsageNote": {
        "nl": "Default waarde voor dit type Feit is \"7008\"."
      },
      "scope": "https://data.vlaanderen.be/id/concept/scope/InPackage",
      "domain": "https://dcjm.data.vlaanderen.be/ns/financiele-data/taxonomie#Code7008",
      "range": {
        "id": "http://www.w3.org/ns/adms#Identifier",
        "vocabularyLabel": {
          "nl": "Identificator"
        },
        "applicationProfileLabel": {
          "nl": "Identificator"
        }
      },
      "minCount": "1",
      "maxCount": "1"
    },
    {
      "id": "https://dcjm.data.vlaanderen.be/ns/financiele-data/taxonomie#DCJMfeit.waarde",
      "vocabularyLabel": {
        "nl": "waarde"
      },
      "applicationProfileLabel": {
        "nl": "waarde"
      },
      "vocabularyDefinition": {
        "nl": "TODO"
      },
      "applicationProfileDefinition": {
        "nl": "TODO"
      },
      "scope": "https://data.vlaanderen.be/id/concept/scope/InPackage",
      "domain": "https://dcjm.data.vlaanderen.be/ns/financiele-data/taxonomie#DCJMfeit",
      "range": {
        "id": "https://schema.org/MonetaryAmount",
        "vocabularyLabel": {
          "nl": "MonetairDatatype"
        },
        "applicationProfileLabel": {
          "nl": "MonetairDatatype"
        }
      },
      "minCount": "1",
      "maxCount": "1"
    }
  ],
  "inPackageMerged": [
    {
      "id": "https://dcjm.data.vlaanderen.be/ns/financiele-data/taxonomie#Code70/76A",
      "vocabularyLabel": {
        "nl": "Bedrijfsopbrengsten"
      },
      "applicationProfileLabel": {
        "nl": "Bedrijfsopbrengsten"
      },
      "vocabularyDefinition": {
        "nl": "Onder de bedrijfsopbrengsten wordt verstaan de opbrengsten die voortvloeien uit de normale exploitatie of uitbating van de organisatie."
      },
      "applicationProfileDefinition": {
        "nl": "Onder de bedrijfsopbrengsten wordt verstaan de opbrengsten die voortvloeien uit de normale exploitatie of uitbating van de organisatie."
      },
      "parents": [
        {
          "id": "https://dcjm.data.vlaanderen.be/ns/financiele-data/taxonomie#DCJMfeit",
          "vocabularyLabel": {
            "nl": "DCJMfeit"
          },
          "applicationProfileLabel": {
            "nl": "DCJMfeit"
          }
        }
      ],
      "scope": "https://data.vlaanderen.be/id/concept/scope/InPackage",
      "properties": [
        {
          "id": "https://dcjm.data.vlaanderen.be/ns/financiele-data/taxonomie#Bedrijfsopbrengsten.balanstype",
          "vocabularyLabel": {
            "nl": "balanstype"
          },
          "applicationProfileLabel": {
            "nl": "balanstype"
          },
          "vocabularyDefinition": {
            "nl": "TODO"
          },
          "applicationProfileDefinition": {
            "nl": "TODO"
          },
          "vocabularyUsageNote": {
            "nl": "Default waarde voor dit type Feit is \"krediet\"."
          },
          "applicationProfileUsageNote": {
            "nl": "Default waarde voor dit type Feit is \"krediet\"."
          },
          "scope": "https://data.vlaanderen.be/id/concept/scope/InPackage",
          "domain": "https://dcjm.data.vlaanderen.be/ns/financiele-data/taxonomie#Code70/76A",
          "range": {
            "id": "http://www.w3.org/2004/02/skos/core#Concept",
            "vocabularyLabel": {
              "nl": "BalansType"
            },
            "applicationProfileLabel": {
              "nl": "BalansType"
            }
          },
          "minCount": "1",
          "maxCount": "1"
        },
        {
          "id": "https://dcjm.data.vlaanderen.be/ns/financiele-data/taxonomie#rubriek",
          "vocabularyLabel": {
            "nl": "rubriek"
          },
          "applicationProfileLabel": {
            "nl": "rubriek"
          },
          "vocabularyDefinition": {
            "nl": "TODO"
          },
          "applicationProfileDefinition": {
            "nl": "TODO"
          },
          "vocabularyUsageNote": {
            "nl": "Default waarde voor dit type Feit is \"70/76A\"."
          },
          "applicationProfileUsageNote": {
            "nl": "Default waarde voor dit type Feit is \"70/76A\"."
          },
          "scope": "https://data.vlaanderen.be/id/concept/scope/InPackage",
          "domain": "https://dcjm.data.vlaanderen.be/ns/financiele-data/taxonomie#Code70/76A",
          "range": {
            "id": "http://www.w3.org/ns/adms#Identifier",
            "vocabularyLabel": {
              "nl": "Identificator"
            },
            "applicationProfileLabel": {
              "nl": "Identificator"
            }
          },
          "minCount": "1",
          "maxCount": "1"
        }
      ]
    },
    {
      "id": "https://dcjm.data.vlaanderen.be/ns/financiele-data/taxonomie#DCJMfeit",
      "vocabularyLabel": {
        "nl": "DCJMfeit"
      },
      "applicationProfileLabel": {
        "nl": "DCJMfeit"
      },
      "vocabularyDefinition": {
        "nl": "TODO"
      },
      "applicationProfileDefinition": {
        "nl": "TODO"
      },
      "parents": [
        {
          "id": "https://data.vlaanderen.be/ns/financiele-rapportering#Feit",
          "vocabularyLabel": {
            "nl": "Feit"
          },
          "applicationProfileLabel": {
            "nl": "Feit"
          }
        }
      ],
      "scope": "https://data.vlaanderen.be/id/concept/scope/InPackage",
      "properties": [
        {
          "id": "https://dcjm.data.vlaanderen.be/ns/financiele-data/taxonomie#DCJMfeit.balanstype",
          "vocabularyLabel": {
            "nl": "balanstype"
          },
          "applicationProfileLabel": {
            "nl": "balanstype"
          },
          "vocabularyDefinition": {
            "nl": "TODO"
          },
          "applicationProfileDefinition": {
            "nl": "TODO"
          },
          "scope": "https://data.vlaanderen.be/id/concept/scope/InPackage",
          "domain": "https://dcjm.data.vlaanderen.be/ns/financiele-data/taxonomie#DCJMfeit",
          "range": {
            "id": "http://www.w3.org/2004/02/skos/core#Concept",
            "vocabularyLabel": {
              "nl": "BalansType"
            },
            "applicationProfileLabel": {
              "nl": "BalansType"
            }
          },
          "minCount": "1",
          "maxCount": "1"
        },
        {
          "id": "https://dcjm.data.vlaanderen.be/ns/financiele-data/taxonomie#DCJMfeit.concept",
          "vocabularyLabel": {
            "nl": "concept"
          },
          "applicationProfileLabel": {
            "nl": "concept"
          },
          "vocabularyDefinition": {
            "nl": "TODO"
          },
          "applicationProfileDefinition": {
            "nl": "TODO"
          },
          "scope": "https://data.vlaanderen.be/id/concept/scope/InPackage",
          "domain": "https://dcjm.data.vlaanderen.be/ns/financiele-data/taxonomie#DCJMfeit",
          "range": {
            "id": "https://data.vlaanderen.be/ns/financiele-rapportering#Concept",
            "vocabularyLabel": {
              "nl": "Concept"
            },
            "applicationProfileLabel": {
              "nl": "Concept"
            }
          },
          "minCount": "0",
          "maxCount": "1"
        },
        {
          "id": "https://dcjm.data.vlaanderen.be/ns/financiele-data/taxonomie#context",
          "vocabularyLabel": {
            "nl": "context"
          },
          "applicationProfileLabel": {
            "nl": "context"
          },
          "vocabularyDefinition": {
            "nl": "TODO"
          },
          "applicationProfileDefinition": {
            "nl": "TODO"
          },
          "scope": "https://data.vlaanderen.be/id/concept/scope/InPackage",
          "domain": "https://dcjm.data.vlaanderen.be/ns/financiele-data/taxonomie#DCJMfeit",
          "range": {
            "id": "https://dcjm.data.vlaanderen.be/ns/financiele-data/taxonomie#HuidigePeriode",
            "vocabularyLabel": {
              "nl": "HuidigePeriode"
            },
            "applicationProfileLabel": {
              "nl": "HuidigePeriode"
            }
          }
        },
        {
          "id": "https://dcjm.data.vlaanderen.be/ns/financiele-data/taxonomie#orde",
          "vocabularyLabel": {
            "nl": "orde"
          },
          "applicationProfileLabel": {
            "nl": "orde"
          },
          "vocabularyDefinition": {
            "nl": "TODO"
          },
          "applicationProfileDefinition": {
            "nl": "TODO"
          },
          "scope": "https://data.vlaanderen.be/id/concept/scope/InPackage",
          "domain": "https://dcjm.data.vlaanderen.be/ns/financiele-data/taxonomie#DCJMfeit",
          "range": {
            "id": "http://www.w3.org/2001/XMLSchema#integer",
            "vocabularyLabel": {
              "nl": "Integer"
            },
            "applicationProfileLabel": {
              "nl": "Integer"
            }
          },
          "minCount": "0",
          "maxCount": "1"
        },
        {
          "id": "https://dcjm.data.vlaanderen.be/ns/financiele-data/taxonomie#DCJMfeit.rapport",
          "vocabularyLabel": {
            "nl": "rapport"
          },
          "applicationProfileLabel": {
            "nl": "rapport"
          },
          "vocabularyDefinition": {
            "nl": "TODO"
          },
          "applicationProfileDefinition": {
            "nl": "TODO"
          },
          "scope": "https://data.vlaanderen.be/id/concept/scope/InPackage",
          "domain": "https://dcjm.data.vlaanderen.be/ns/financiele-data/taxonomie#DCJMfeit",
          "range": {
            "id": "https://data.vlaanderen.be/ns/financiele-rapportering#FinancieelRapport",
            "vocabularyLabel": {
              "nl": "FinancieelRapport"
            },
            "applicationProfileLabel": {
              "nl": "FinancieelRapport"
            }
          },
          "minCount": "1",
          "maxCount": "1"
        },
        {
          "id": "https://dcjm.data.vlaanderen.be/ns/financiele-data/taxonomie#DCJMfeit.rubriek",
          "vocabularyLabel": {
            "nl": "rubriek"
          },
          "applicationProfileLabel": {
            "nl": "rubriek"
          },
          "vocabularyDefinition": {
            "nl": "TODO"
          },
          "applicationProfileDefinition": {
            "nl": "TODO"
          },
          "scope": "https://data.vlaanderen.be/id/concept/scope/InPackage",
          "domain": "https://dcjm.data.vlaanderen.be/ns/financiele-data/taxonomie#DCJMfeit",
          "range": {
            "id": "http://www.w3.org/ns/adms#Identifier",
            "vocabularyLabel": {
              "nl": "Identificator"
            },
            "applicationProfileLabel": {
              "nl": "Identificator"
            }
          },
          "minCount": "1",
          "maxCount": "1"
        },
        {
          "id": "https://dcjm.data.vlaanderen.be/ns/financiele-data/taxonomie#DCJMfeit.waarde",
          "vocabularyLabel": {
            "nl": "waarde"
          },
          "applicationProfileLabel": {
            "nl": "waarde"
          },
          "vocabularyDefinition": {
            "nl": "TODO"
          },
          "applicationProfileDefinition": {
            "nl": "TODO"
          },
          "scope": "https://data.vlaanderen.be/id/concept/scope/InPackage",
          "domain": "https://dcjm.data.vlaanderen.be/ns/financiele-data/taxonomie#DCJMfeit",
          "range": {
            "id": "https://schema.org/MonetaryAmount",
            "vocabularyLabel": {
              "nl": "MonetairDatatype"
            },
            "applicationProfileLabel": {
              "nl": "MonetairDatatype"
            }
          },
          "minCount": "1",
          "maxCount": "1"
        }
      ]
    },
    {
      "id": "https://dcjm.data.vlaanderen.be/ns/financiele-data/taxonomie#Code7005",
      "vocabularyLabel": {
        "nl": "Donatie met tegenprestatie"
      },
      "applicationProfileLabel": {
        "nl": "Donatie met tegenprestatie"
      },
      "vocabularyDefinition": {
        "nl": "NOTE"
      },
      "applicationProfileDefinition": {
        "nl": "NOTE"
      },
      "parents": [
        {
          "id": "https://dcjm.data.vlaanderen.be/ns/financiele-data/taxonomie#Code700",
          "vocabularyLabel": {
            "nl": "Inkomgelden en vergoedingen uit eigen activiteiten"
          },
          "applicationProfileLabel": {
            "nl": "Inkomgelden en vergoedingen uit eigen activiteiten"
          }
        }
      ],
      "scope": "https://data.vlaanderen.be/id/concept/scope/InPackage",
      "properties": [
        {
          "id": "https://dcjm.data.vlaanderen.be/ns/financiele-data/taxonomie#Code7005.rubriek",
          "vocabularyLabel": {
            "nl": "rubriek"
          },
          "applicationProfileLabel": {
            "nl": "rubriek"
          },
          "vocabularyDefinition": {
            "nl": "TODO"
          },
          "applicationProfileDefinition": {
            "nl": "TODO"
          },
          "vocabularyUsageNote": {
            "nl": "Default waarde voor dit type Feit is \"7005\"."
          },
          "applicationProfileUsageNote": {
            "nl": "Default waarde voor dit type Feit is \"7005\"."
          },
          "scope": "https://data.vlaanderen.be/id/concept/scope/InPackage",
          "domain": "https://dcjm.data.vlaanderen.be/ns/financiele-data/taxonomie#Code7005",
          "range": {
            "id": "http://www.w3.org/ns/adms#Identifier",
            "vocabularyLabel": {
              "nl": "Identificator"
            },
            "applicationProfileLabel": {
              "nl": "Identificator"
            }
          },
          "minCount": "1",
          "maxCount": "1"
        }
      ]
    },
    {
      "id": "https://dcjm.data.vlaanderen.be/ns/financiele-data/taxonomie#HuidigePeriode",
      "vocabularyLabel": {
        "nl": "HuidigePeriode"
      },
      "applicationProfileLabel": {
        "nl": "HuidigePeriode"
      },
      "vocabularyDefinition": {
        "nl": "De Context van dit feit."
      },
      "applicationProfileDefinition": {
        "nl": "De Context van dit feit."
      },
      "parents": [
        {
          "id": "https://data.vlaanderen.be/ns/financiele-rapportering#Context",
          "vocabularyLabel": {
            "nl": "Context"
          },
          "applicationProfileLabel": {
            "nl": "Context"
          }
        }
      ],
      "scope": "https://data.vlaanderen.be/id/concept/scope/InPackage",
      "properties": [
        {
          "id": "https://dcjm.data.vlaanderen.be/ns/financiele-data/taxonomie#HuidigePeriode.entiteit",
          "vocabularyLabel": {
            "nl": "entiteit"
          },
          "applicationProfileLabel": {
            "nl": "entiteit"
          },
          "vocabularyDefinition": {
            "nl": "TODO"
          },
          "applicationProfileDefinition": {
            "nl": "TODO"
          },
          "scope": "https://data.vlaanderen.be/id/concept/scope/InPackage",
          "domain": "https://dcjm.data.vlaanderen.be/ns/financiele-data/taxonomie#HuidigePeriode",
          "range": {
            "id": "http://www.w3.org/ns/org#Organization",
            "vocabularyLabel": {
              "nl": "Organisatie"
            },
            "applicationProfileLabel": {
              "nl": "Organisatie"
            }
          },
          "minCount": "1",
          "maxCount": "1"
        },
        {
          "id": "https://dcjm.data.vlaanderen.be/ns/financiele-data/taxonomie#Code70/76AContext.periode",
          "vocabularyLabel": {
            "nl": "periode"
          },
          "applicationProfileLabel": {
            "nl": "periode"
          },
          "vocabularyDefinition": {
            "nl": "TODO"
          },
          "applicationProfileDefinition": {
            "nl": "TODO"
          },
          "scope": "https://data.vlaanderen.be/id/concept/scope/InPackage",
          "domain": "https://dcjm.data.vlaanderen.be/ns/financiele-data/taxonomie#HuidigePeriode",
          "range": {
            "id": "http://def.isotc211.org/iso19108/2006/TemporalObjects#TM_Instant",
            "vocabularyLabel": {
              "nl": "Moment"
            },
            "applicationProfileLabel": {
              "nl": "Moment"
            }
          },
          "minCount": "1",
          "maxCount": "1"
        },
        {
          "id": "https://dcjm.data.vlaanderen.be/ns/financiele-data/taxonomie#HuidigePeriode.rapport",
          "vocabularyLabel": {
            "nl": "rapport"
          },
          "applicationProfileLabel": {
            "nl": "rapport"
          },
          "vocabularyDefinition": {
            "nl": "TODO"
          },
          "applicationProfileDefinition": {
            "nl": "TODO"
          },
          "scope": "https://data.vlaanderen.be/id/concept/scope/InPackage",
          "domain": "https://dcjm.data.vlaanderen.be/ns/financiele-data/taxonomie#HuidigePeriode",
          "range": {
            "id": "https://data.vlaanderen.be/ns/financiele-rapportering#FinancieelRapport",
            "vocabularyLabel": {
              "nl": "FinancieelRapport"
            },
            "applicationProfileLabel": {
              "nl": "FinancieelRapport"
            }
          },
          "minCount": "1",
          "maxCount": "1"
        }
      ]
    },
    {
      "id": "https://dcjm.data.vlaanderen.be/ns/financiele-data/taxonomie#Code700",
      "vocabularyLabel": {
        "nl": "Inkomgelden en vergoedingen uit eigen activiteiten"
      },
      "applicationProfileLabel": {
        "nl": "Inkomgelden en vergoedingen uit eigen activiteiten"
      },
      "vocabularyDefinition": {
        "nl": "NOTE"
      },
      "applicationProfileDefinition": {
        "nl": "NOTE"
      },
      "parents": [
        {
          "id": "https://dcjm.data.vlaanderen.be/ns/financiele-data/taxonomie#Code70",
          "vocabularyLabel": {
            "nl": "Omzet"
          },
          "applicationProfileLabel": {
            "nl": "Omzet"
          }
        }
      ],
      "scope": "https://data.vlaanderen.be/id/concept/scope/InPackage",
      "properties": [
        {
          "id": "https://dcjm.data.vlaanderen.be/ns/financiele-data/taxonomie#Code700.rubriek",
          "vocabularyLabel": {
            "nl": "rubriek"
          },
          "applicationProfileLabel": {
            "nl": "rubriek"
          },
          "vocabularyDefinition": {
            "nl": "TODO"
          },
          "applicationProfileDefinition": {
            "nl": "TODO"
          },
          "vocabularyUsageNote": {
            "nl": "Default waarde voor dit type Feit is \"700\"."
          },
          "applicationProfileUsageNote": {
            "nl": "Default waarde voor dit type Feit is \"700\"."
          },
          "scope": "https://data.vlaanderen.be/id/concept/scope/InPackage",
          "domain": "https://dcjm.data.vlaanderen.be/ns/financiele-data/taxonomie#Code700",
          "range": {
            "id": "http://www.w3.org/ns/adms#Identifier",
            "vocabularyLabel": {
              "nl": "Identificator"
            },
            "applicationProfileLabel": {
              "nl": "Identificator"
            }
          },
          "minCount": "1",
          "maxCount": "1"
        }
      ]
    },
    {
      "id": "https://dcjm.data.vlaanderen.be/ns/financiele-data/taxonomie#Code7001",
      "vocabularyLabel": {
        "nl": "Inschrijvingsgelden en ticketverkoop"
      },
      "applicationProfileLabel": {
        "nl": "Inschrijvingsgelden en ticketverkoop"
      },
      "vocabularyDefinition": {
        "nl": "NOTE"
      },
      "applicationProfileDefinition": {
        "nl": "NOTE"
      },
      "parents": [
        {
          "id": "https://dcjm.data.vlaanderen.be/ns/financiele-data/taxonomie#Code700",
          "vocabularyLabel": {
            "nl": "Inkomgelden en vergoedingen uit eigen activiteiten"
          },
          "applicationProfileLabel": {
            "nl": "Inkomgelden en vergoedingen uit eigen activiteiten"
          }
        }
      ],
      "scope": "https://data.vlaanderen.be/id/concept/scope/InPackage",
      "properties": [
        {
          "id": "https://dcjm.data.vlaanderen.be/ns/financiele-data/taxonomie#Code7001.rubriek",
          "vocabularyLabel": {
            "nl": "rubriek"
          },
          "applicationProfileLabel": {
            "nl": "rubriek"
          },
          "vocabularyDefinition": {
            "nl": "TODO"
          },
          "applicationProfileDefinition": {
            "nl": "TODO"
          },
          "vocabularyUsageNote": {
            "nl": "Default waarde voor dit type Feit is \"7001\"."
          },
          "applicationProfileUsageNote": {
            "nl": "Default waarde voor dit type Feit is \"7001\"."
          },
          "scope": "https://data.vlaanderen.be/id/concept/scope/InPackage",
          "domain": "https://dcjm.data.vlaanderen.be/ns/financiele-data/taxonomie#Code7001",
          "range": {
            "id": "http://www.w3.org/ns/adms#Identifier",
            "vocabularyLabel": {
              "nl": "Identificator"
            },
            "applicationProfileLabel": {
              "nl": "Identificator"
            }
          },
          "minCount": "1",
          "maxCount": "1"
        }
      ]
    },
    {
      "id": "https://dcjm.data.vlaanderen.be/ns/financiele-data/taxonomie#Code70",
      "vocabularyLabel": {
        "nl": "Omzet"
      },
      "applicationProfileLabel": {
        "nl": "Omzet"
      },
      "vocabularyDefinition": {
        "nl": "NOTE"
      },
      "applicationProfileDefinition": {
        "nl": "NOTE"
      },
      "parents": [
        {
          "id": "https://dcjm.data.vlaanderen.be/ns/financiele-data/taxonomie#Code70/76A",
          "vocabularyLabel": {
            "nl": "Bedrijfsopbrengsten"
          },
          "applicationProfileLabel": {
            "nl": "Bedrijfsopbrengsten"
          }
        }
      ],
      "scope": "https://data.vlaanderen.be/id/concept/scope/InPackage",
      "properties": [
        {
          "id": "https://dcjm.data.vlaanderen.be/ns/financiele-data/taxonomie#Code70.rubriek",
          "vocabularyLabel": {
            "nl": "rubriek"
          },
          "applicationProfileLabel": {
            "nl": "rubriek"
          },
          "vocabularyDefinition": {
            "nl": "TODO"
          },
          "applicationProfileDefinition": {
            "nl": "TODO"
          },
          "vocabularyUsageNote": {
            "nl": "Default waarde voor dit type Feit is \"70\"."
          },
          "applicationProfileUsageNote": {
            "nl": "Default waarde voor dit type Feit is \"70\"."
          },
          "scope": "https://data.vlaanderen.be/id/concept/scope/InPackage",
          "domain": "https://dcjm.data.vlaanderen.be/ns/financiele-data/taxonomie#Code70",
          "range": {
            "id": "http://www.w3.org/ns/adms#Identifier",
            "vocabularyLabel": {
              "nl": "Identificator"
            },
            "applicationProfileLabel": {
              "nl": "Identificator"
            }
          },
          "minCount": "1",
          "maxCount": "1"
        }
      ]
    },
    {
      "id": "https://dcjm.data.vlaanderen.be/ns/financiele-data/taxonomie#Code7008",
      "vocabularyLabel": {
        "nl": "Overige vergoedingen"
      },
      "applicationProfileLabel": {
        "nl": "Overige vergoedingen"
      },
      "vocabularyDefinition": {
        "nl": "Deze rubriek bevat alle opbrengsten die tot de omzet behoren en die voortvloeien uit Inkomgelden en vergoedingen uit eigen activiteiten van de VZW, IVZW of Stichting, maar die niet in één van de andere beschikbare rubrieken kunnen worden ondergebracht."
      },
      "applicationProfileDefinition": {
        "nl": "Deze rubriek bevat alle opbrengsten die tot de omzet behoren en die voortvloeien uit Inkomgelden en vergoedingen uit eigen activiteiten van de VZW, IVZW of Stichting, maar die niet in één van de andere beschikbare rubrieken kunnen worden ondergebracht."
      },
      "parents": [
        {
          "id": "https://dcjm.data.vlaanderen.be/ns/financiele-data/taxonomie#Code700",
          "vocabularyLabel": {
            "nl": "Inkomgelden en vergoedingen uit eigen activiteiten"
          },
          "applicationProfileLabel": {
            "nl": "Inkomgelden en vergoedingen uit eigen activiteiten"
          }
        }
      ],
      "scope": "https://data.vlaanderen.be/id/concept/scope/InPackage",
      "properties": [
        {
          "id": "https://dcjm.data.vlaanderen.be/ns/financiele-data/taxonomie#Code7008.rubriek",
          "vocabularyLabel": {
            "nl": "rubriek"
          },
          "applicationProfileLabel": {
            "nl": "rubriek"
          },
          "vocabularyDefinition": {
            "nl": "TODO"
          },
          "applicationProfileDefinition": {
            "nl": "TODO"
          },
          "vocabularyUsageNote": {
            "nl": "Default waarde voor dit type Feit is \"7008\"."
          },
          "applicationProfileUsageNote": {
            "nl": "Default waarde voor dit type Feit is \"7008\"."
          },
          "scope": "https://data.vlaanderen.be/id/concept/scope/InPackage",
          "domain": "https://dcjm.data.vlaanderen.be/ns/financiele-data/taxonomie#Code7008",
          "range": {
            "id": "http://www.w3.org/ns/adms#Identifier",
            "vocabularyLabel": {
              "nl": "Identificator"
            },
            "applicationProfileLabel": {
              "nl": "Identificator"
            }
          },
          "minCount": "1",
          "maxCount": "1"
        }
      ]
    }
  ]
}