{
  "metadata": {
    "title": "OSLO Services",
    "uri": "https://data.vlaanderen.be/ns/nutsvoorzieningen",
    "issued": "2024-01-26",
    "filename": "nutsvoorzieningen",
    "navigation": {
      "self": "https://data.test-vlaanderen.be/doc/vocabularium/nutsvoorzieningen/kandidaatstandaard/2024-01-26"
    },
    "license": "https://data.vlaanderen.be/id/licentie/modellicentie-gratis-hergebruik/v1.0",
    "documenttype": "voc",
    "documentconfig": {},
    "status": "https://data.vlaanderen.be/id/concept/StandaardStatus/ErkendeStandaard",
    "statuslabel": "Erkende Standaard",
    "repositoryurl": "https://github.com/Informatievlaanderen/OSLOthema-imkl/tree/43ba8f820b275119b86f1e9878ef0b9fb52527ef",
    "changelogurl": "https://github.com/Informatievlaanderen/OSLOthema-imkl/blob/43ba8f820b275119b86f1e9878ef0b9fb52527ef/CHANGELOG",
    "feedbackurl": "https://github.com/Informatievlaanderen/OSLOthema-imkl/issues",
    "standaardregisterurl": "https://data.vlaanderen.be/standaarden/standaard-in-ontwikkeling/vocabularium-nutsvoorzieningen.html",
    "usesVocs": [],
    "usesAPs": []
  },
  "classes": [
    {
      "uri": "https://data.vlaanderen.be/ns/nutsvoorzieningen#Aansluiting",
      "name": "Aansluiting",
      "label": {
        "fr": "Enter your translation here",
        "nl": "Aansluiting"
      },
      "sort": "Enter your translation here",
      "description": {
        "fr": "Enter your translation here",
        "nl": "Object dat de aansluiting van een kabel of leiding aan een gebouw of een ander fysiek object beschrijft"
      },
      "usage": {},
      "equivalent": [],
      "parents": [
        "https://data.vlaanderen.be/ns/nutsvoorzieningen#Toebehoren"
      ]
    },
    {
      "uri": "https://data.vlaanderen.be/ns/nutsvoorzieningen#Annotatie",
      "name": "Annotatie",
      "label": {
        "fr": "Enter your translation here",
        "nl": "Annotatie"
      },
      "sort": "Enter your translation here",
      "description": {
        "fr": "Enter your translation here",
        "nl": "Een korte uitleg of notitie toegevoegd aan een Object."
      },
      "usage": {
        "fr": "Enter your translation here",
        "nl": "In deze context typisch Maataanduiding op een kabel- of leidingenkaart, bvb de afstand van een kabel tov een gevel. Kan bestaan uit onderdelen (bvb maatvoeringslijn, maatvoeringshulplijn, twee pijlen) die op zich ook Annotaties zijn."
      },
      "equivalent": [],
      "parents": []
    },
    {
      "uri": "https://data.vlaanderen.be/ns/nutsvoorzieningen#BeschermdGebied",
      "name": "BeschermdGebied",
      "label": {
        "fr": "Enter your translation here",
        "nl": "Beschermd Gebied"
      },
      "sort": "Enter your translation here",
      "description": {
        "fr": "Enter your translation here",
        "nl": "Gebied waar niet gegraven mag worden."
      },
      "usage": {},
      "equivalent": [],
      "parents": []
    },
    {
      "uri": "https://data.vlaanderen.be/ns/nutsvoorzieningen#Diepte",
      "name": "Diepte",
      "label": {
        "fr": "Enter your translation here",
        "nl": "Diepte"
      },
      "sort": "Enter your translation here",
      "description": {
        "fr": "Enter your translation here",
        "nl": "VerticalePositie onder het Referentieoppervlak."
      },
      "usage": {},
      "equivalent": [],
      "parents": [
        "https://data.vlaanderen.be/ns/nutsvoorzieningen#VerticalePositie"
      ]
    },
    {
      "uri": "https://data.vlaanderen.be/ns/nutsvoorzieningen#Electriciteitskabel",
      "name": "Electriciteitskabel",
      "label": {
        "fr": "Enter your translation here",
        "nl": "Electriciteitskabel"
      },
      "sort": "Enter your translation here",
      "description": {
        "fr": "Enter your translation here",
        "nl": "Een Kabel gebruikt om elektriciteit van de ene naar de andere locatie te transporteren."
      },
      "usage": {},
      "equivalent": [],
      "parents": [
        "https://data.vlaanderen.be/ns/nutsvoorzieningen#Kabel"
      ]
    },
    {
      "uri": "https://data.vlaanderen.be/ns/nutsvoorzieningen#Hoogte",
      "name": "Hoogte",
      "label": {
        "fr": "Enter your translation here",
        "nl": "Hoogte"
      },
      "sort": "Enter your translation here",
      "description": {
        "fr": "Enter your translation here",
        "nl": "VerticalePositie boven het Referentieoppervlak."
      },
      "usage": {},
      "equivalent": [],
      "parents": [
        "https://data.vlaanderen.be/ns/nutsvoorzieningen#VerticalePositie"
      ]
    },
    {
      "uri": "https://data.vlaanderen.be/ns/nutsvoorzieningen#Kabel",
      "name": "Kabel",
      "label": {
        "fr": "Enter your translation here",
        "nl": "Kabel"
      },
      "sort": "Enter your translation here",
      "description": {
        "fr": "Enter your translation here",
        "nl": "Een Nutsvoorzieninglinkset gebruikt om elektriciteit of gegevens van de ene locatie naar de andere over te brengen."
      },
      "usage": {},
      "equivalent": [],
      "parents": [
        "https://data.vlaanderen.be/ns/nutsvoorzieningen#Nutsvoorzieninglinkset"
      ]
    },
    {
      "uri": "https://data.vlaanderen.be/ns/nutsvoorzieningen#KabelEnLeidingContainer",
      "name": "Kabelenleidingcontainer",
      "label": {
        "fr": "Enter your translation here",
        "nl": "KabelEnLeidingContainer"
      },
      "sort": "Enter your translation here",
      "description": {
        "fr": "Enter your translation here",
        "nl": "Object dat potentieel kabels of leidingen kan omvatten."
      },
      "usage": {
        "fr": "Enter your translation here",
        "nl": "Bvb als het object een Pijp is: een Pijp kan Kabels omvatten of andere Pijpen. Analoog voor leidingen vh type Kanaal. Kabels zijn geen KabelEnLeidingContainers. OPMERKING: of de KabelOfLeidingContainer uiteindelijk andere elementen bevat wortdt weergegeven door de uitgaande relaties naar die andere relaties (bvb Kanaal.pijp, Pijp.kabel, Kanaal.kabel, Pijp.pijp etc)."
      },
      "equivalent": [],
      "parents": []
    },
    {
      "uri": "https://data.vlaanderen.be/ns/nutsvoorzieningen#Kanaal",
      "name": "Kanaal",
      "label": {
        "fr": "Enter your translation here",
        "nl": "Kanaal"
      },
      "sort": "Enter your translation here",
      "description": {
        "fr": "Enter your translation here",
        "nl": "Een Nutsvoorzieninglinkset gebruikt om kabels en leidingen te beschermen en te geleiden via een omhullende constructie."
      },
      "usage": {},
      "equivalent": [],
      "parents": [
        "https://data.vlaanderen.be/ns/nutsvoorzieningen#Nutsvoorzieninglinkset",
        "https://data.vlaanderen.be/ns/nutsvoorzieningen#KabelEnLeidingContainer"
      ]
    },
    {
      "uri": "https://data.vlaanderen.be/ns/nutsvoorzieningen#Kast",
      "name": "Kast",
      "label": {
        "fr": "Enter your translation here",
        "nl": "Kast"
      },
      "sort": "Enter your translation here",
      "description": {
        "fr": "Enter your translation here",
        "nl": "Eenvoudige Nutsvoorzieningknoopcontainer die de vorm aanneemt van een kast."
      },
      "usage": {
        "fr": "Enter your translation here",
        "nl": "Bevat typisch kleiner monteerbaar Toebehoren en Kabels."
      },
      "equivalent": [],
      "parents": [
        "https://data.vlaanderen.be/ns/nutsvoorzieningen#Nutsvoorzieningknoopcontainer"
      ]
    },
    {
      "uri": "https://data.vlaanderen.be/ns/nutsvoorzieningen#Maataanduiding",
      "name": "Maataanduiding",
      "label": {
        "fr": "Enter your translation here",
        "nl": "Maataanduiding"
      },
      "sort": "Enter your translation here",
      "description": {
        "fr": "Enter your translation here",
        "nl": "Soort Annotatie dat de maat van een Object aangeeft."
      },
      "usage": {
        "fr": "Enter your translation here",
        "nl": "Bv de afmetingen van een kamer."
      },
      "equivalent": [],
      "parents": [
        "https://data.vlaanderen.be/ns/nutsvoorzieningen#Annotatie"
      ]
    },
    {
      "uri": "https://data.vlaanderen.be/ns/nutsvoorzieningen#Mangat",
      "name": "Mangat",
      "label": {
        "fr": "Enter your translation here",
        "nl": "Mangat"
      },
      "sort": "Enter your translation here",
      "description": {
        "fr": "Enter your translation here",
        "nl": "Eenvoudige Nutsvoorzieningknoopcontainer die de vorm aanneemt van een afgedekte opening in het wegdek die toegang verschaft tot de ondergrond."
      },
      "usage": {
        "fr": "Enter your translation here",
        "nl": "Bvb riooldeksel."
      },
      "equivalent": [],
      "parents": [
        "https://data.vlaanderen.be/ns/nutsvoorzieningen#Nutsvoorzieningknoopcontainer"
      ]
    },
    {
      "uri": "https://data.vlaanderen.be/ns/nutsvoorzieningen#Nutsvoorzieningknoop",
      "name": "Nutsvoorzieningknoop",
      "label": {
        "fr": "Enter your translation here",
        "nl": "Nutsvoorzieningknoop"
      },
      "sort": "Enter your translation here",
      "description": {
        "fr": "Enter your translation here",
        "nl": "Puntvormig ruimtelijk object dat een rol van belang vervult in een Nutsvoorzieningnetwerk."
      },
      "usage": {
        "fr": "Enter your translation here",
        "nl": "Kan op zichzelf staan of begin of einde vormen van een Nutsvoorzieninglink. OPMERKING: is abstract, moet verder gespecialiseerd worden als Toebehoren of een subklasse daarvan."
      },
      "equivalent": [],
      "parents": [
        "https://data.vlaanderen.be/ns/netwerk#Knoop",
        "https://data.vlaanderen.be/ns/nutsvoorzieningen#Nutsvoorzieningnetwerkelement"
      ]
    },
    {
      "uri": "https://data.vlaanderen.be/ns/nutsvoorzieningen#Nutsvoorzieningknoopcontainer",
      "name": "Nutsvoorzieningknoopcontainer",
      "label": {
        "fr": "Enter your translation here",
        "nl": "Nutsvoorzieningknoopcontainer"
      },
      "sort": "Enter your translation here",
      "description": {
        "fr": "Enter your translation here",
        "nl": "Puntvormig Nutsvoorzieningnetwerkelement, potentieel drager van Nutsvoorzieningknopen."
      },
      "usage": {
        "fr": "Enter your translation here",
        "nl": "Bvb Toren, Paal, Mangat, Kast. Bvb een Kast bevat schakelaars, aansluitingen etc die Knopen vormen in het Nutsvoorzieningnetwerk."
      },
      "equivalent": [],
      "parents": [
        "https://data.vlaanderen.be/ns/nutsvoorzieningen#Nutsvoorzieningnetwerkelement"
      ]
    },
    {
      "uri": "https://data.vlaanderen.be/ns/nutsvoorzieningen#Nutsvoorzieninglink",
      "name": "Nutsvoorzieninglink",
      "label": {
        "fr": "Enter your translation here",
        "nl": "Nutsvoorzieninglink"
      },
      "sort": "Enter your translation here",
      "description": {
        "fr": "Enter your translation here",
        "nl": "Een lineair ruimtelijk object dat de geometrie en connectiviteit beschrijft tussen twee punten in een Nutsvoorzieningnetwerk."
      },
      "usage": {},
      "equivalent": [],
      "parents": [
        "https://data.vlaanderen.be/ns/nutsvoorzieningen#Nutsvoorzieningnetwerkelement",
        "https://data.vlaanderen.be/ns/netwerk#Link"
      ]
    },
    {
      "uri": "https://data.vlaanderen.be/ns/nutsvoorzieningen#Nutsvoorzieninglinksequentie",
      "name": "Nutsvoorzieninglinksequentie",
      "label": {
        "fr": "Enter your translation here",
        "nl": "Nutsvoorzieninglinksequentie"
      },
      "sort": "Enter your translation here",
      "description": {
        "fr": "Enter your translation here",
        "nl": "Een onvertakt doorlopend pad in het Nutsvoorzieningnetwerk."
      },
      "usage": {
        "fr": "Enter your translation here",
        "nl": "In feite een route in het netwerk, bvb een waterleiding in de stroomrichting. Routes hebben een richting, daarom is de Linksequentie samengesteld uit GerichteLinks."
      },
      "equivalent": [],
      "parents": [
        "https://data.vlaanderen.be/ns/nutsvoorzieningen#Nutsvoorzieningnetwerkelement",
        "https://data.vlaanderen.be/ns/netwerk#Linksequentie"
      ]
    },
    {
      "uri": "https://data.vlaanderen.be/ns/nutsvoorzieningen#Nutsvoorzieninglinkset",
      "name": "Nutsvoorzieninglinkset",
      "label": {
        "fr": "Enter your translation here",
        "nl": "Nutsvoorzieninglinkset"
      },
      "sort": "Enter your translation here",
      "description": {
        "fr": "Enter your translation here",
        "nl": "Collectie lineaire ruimtelijke objecten met een specifieke functie of belang in het Nutsvoorzieningnetwerk."
      },
      "usage": {
        "fr": "Enter your translation here",
        "nl": "In praktijk een collectie van Nutsvoorzieninglinksequenties en/of Nutsvoorzieninglinks. OPMERKING: is abstract, moet verder gespecialiseerd worden bvb als Electriciteitskabel, Rioolpijp etc."
      },
      "equivalent": [],
      "parents": [
        "https://data.vlaanderen.be/ns/nutsvoorzieningen#Nutsvoorzieningnetwerkelement",
        "https://data.vlaanderen.be/ns/netwerk#Linkset"
      ]
    },
    {
      "uri": "https://data.vlaanderen.be/ns/nutsvoorzieningen#Nutsvoorzieningnetwerk",
      "name": "Nutsvoorzieningnetwerk",
      "label": {
        "fr": "Enter your translation here",
        "nl": "Nutsvoorzieningnetwerk"
      },
      "sort": "Enter your translation here",
      "description": {
        "fr": "Enter your translation here",
        "nl": "Verzameling van netwerkelementen van één type nutsvoorziening."
      },
      "usage": {
        "fr": "Enter your translation here",
        "nl": "Bvb een electriciteitsnet, een rioleringsnet, een gasnet. De netwerkelementen waarvan sprake zijn bvb de elementen van het netwerk van een aanbiedervan internet: optische kabels aankomend in kasten op straat via multiplexers verbonden met koperkabels naar de woningen in die straat."
      },
      "equivalent": [],
      "parents": [
        "https://data.vlaanderen.be/ns/netwerk#Netwerk"
      ]
    },
    {
      "uri": "https://data.vlaanderen.be/ns/nutsvoorzieningen#Nutsvoorzieningnetwerkelement",
      "name": "Nustvoorzieningnetwerkelement",
      "label": {
        "fr": "Enter your translation here",
        "nl": "Nustvoorzieningnetwerkelement"
      },
      "sort": "Enter your translation here",
      "description": {
        "fr": "Enter your translation here",
        "nl": "Element in een Nutsvoorzieningnetwerk dat daarin een functie van belang vervult."
      },
      "usage": {
        "fr": "Enter your translation here",
        "nl": "OPMERKING: is abstract, moet gespecialiseerd worden (bvb als Electriciteitskabel, Riooolpijp, Mangat, Kast etc)."
      },
      "equivalent": [],
      "parents": []
    },
    {
      "uri": "https://data.vlaanderen.be/ns/nutsvoorzieningen#OlieGasChemicalienPijp",
      "name": "Oliegaschemicaliënpijp",
      "label": {
        "fr": "Enter your translation here",
        "nl": "OlieGasChemicaliënPijp"
      },
      "sort": "Enter your translation here",
      "description": {
        "fr": "Enter your translation here",
        "nl": "Een pijp die wordt gebruikt om olie, gas of chemicaliën van de ene locatie naar de andere te transporteren."
      },
      "usage": {},
      "equivalent": [],
      "parents": [
        "https://data.vlaanderen.be/ns/nutsvoorzieningen#Pijp"
      ]
    },
    {
      "uri": "https://data.vlaanderen.be/ns/nutsvoorzieningen#Paal",
      "name": "Paal",
      "label": {
        "fr": "Enter your translation here",
        "nl": "Paal"
      },
      "sort": "Enter your translation here",
      "description": {
        "fr": "Enter your translation here",
        "nl": "Eenvoudige Nutsvoorzieningenknoopcontainer die de vorm aanneemt van een mast."
      },
      "usage": {
        "fr": "Enter your translation here",
        "nl": "Typisch drager van monteerbaar Toebehoren en Kabels."
      },
      "equivalent": [],
      "parents": [
        "https://data.vlaanderen.be/ns/nutsvoorzieningen#Nutsvoorzieningknoopcontainer"
      ]
    },
    {
      "uri": "https://data.vlaanderen.be/ns/nutsvoorzieningen#Pijp",
      "name": "Pijp",
      "label": {
        "fr": "Enter your translation here",
        "nl": "Pijp"
      },
      "sort": "Enter your translation here",
      "description": {
        "fr": "Enter your translation here",
        "nl": "Een Nutsvoorzieninglinkset voor het transport van vaste stoffen, vloeistoffen, chemicaliën of gassen van de ene locatie naar de andere."
      },
      "usage": {},
      "equivalent": [],
      "parents": [
        "https://data.vlaanderen.be/ns/nutsvoorzieningen#Nutsvoorzieninglinkset",
        "https://data.vlaanderen.be/ns/nutsvoorzieningen#KabelEnLeidingContainer"
      ]
    },
    {
      "uri": "https://data.vlaanderen.be/ns/nutsvoorzieningen#Plan",
      "name": "Plan",
      "label": {
        "fr": "Enter your translation here",
        "nl": "Plan"
      },
      "sort": "Enter your translation here",
      "description": {
        "fr": "Enter your translation here",
        "nl": "Tekening met de onderdelen of details van iets."
      },
      "usage": {
        "fr": "Enter your translation here",
        "nl": "Bvb plattegrond, stratenplan."
      },
      "equivalent": [],
      "parents": [
        "http://xmlns.com/foaf/0.1/Document"
      ]
    },
    {
      "uri": "https://data.vlaanderen.be/ns/nutsvoorzieningen#Referentieoppervlak",
      "name": "Referentieoppervlak",
      "label": {
        "fr": "Enter your translation here",
        "nl": "Referentieoppervlak"
      },
      "sort": "Enter your translation here",
      "description": {
        "fr": "Enter your translation here",
        "nl": "Oppervlak tov waarvan een positie wordt gemeten."
      },
      "usage": {
        "fr": "Enter your translation here",
        "nl": "In deze context typisch het maaiveld."
      },
      "equivalent": [],
      "parents": []
    },
    {
      "uri": "https://data.vlaanderen.be/ns/nutsvoorzieningen#Rioolpijp",
      "name": "Rioolpijp",
      "label": {
        "fr": "Enter your translation here",
        "nl": "Rioolpijp"
      },
      "sort": "Enter your translation here",
      "description": {
        "fr": "Enter your translation here",
        "nl": "Een buis die wordt gebruikt om afvalwater van de ene locatie naar de andere te transporteren."
      },
      "usage": {},
      "equivalent": [],
      "parents": [
        "https://data.vlaanderen.be/ns/nutsvoorzieningen#Pijp"
      ]
    },
    {
      "uri": "https://data.vlaanderen.be/ns/nutsvoorzieningen#Telecommunicatiekabel",
      "name": "Telecommunicatiekabel",
      "label": {
        "fr": "Enter your translation here",
        "nl": "Telecommunicatiekabel"
      },
      "sort": "Enter your translation here",
      "description": {
        "fr": "Enter your translation here",
        "nl": "Een Nutsvoorzieninglinkset die wordt gebruikt om datasignalen (PSTN, radio of computer) van de ene locatie naar de andere te transporteren."
      },
      "usage": {},
      "equivalent": [],
      "parents": [
        "https://data.vlaanderen.be/ns/nutsvoorzieningen#Kabel"
      ]
    },
    {
      "uri": "https://data.vlaanderen.be/ns/nutsvoorzieningen#ThermischePijp",
      "name": "Thermischepijp",
      "label": {
        "fr": "Enter your translation here",
        "nl": "ThermischePijp"
      },
      "sort": "Enter your translation here",
      "description": {
        "fr": "Enter your translation here",
        "nl": "Een Pijp die wordt gebruikt om verwarming of koeling van de ene locatie naar de andere te transporteren."
      },
      "usage": {},
      "equivalent": [],
      "parents": [
        "https://data.vlaanderen.be/ns/nutsvoorzieningen#Pijp"
      ]
    },
    {
      "uri": "https://data.vlaanderen.be/ns/nutsvoorzieningen#Toebehoren",
      "name": "Toebehoren",
      "label": {
        "fr": "Enter your translation here",
        "nl": "Toebehoren"
      },
      "sort": "Enter your translation here",
      "description": {
        "fr": "Enter your translation here",
        "nl": "Fysiek puntvormig onderdeel van het Nutsvoorzieningnetwerk."
      },
      "usage": {
        "fr": "Enter your translation here",
        "nl": "Kan als Nutsvoorzieningknoop op zichzelf staan maar is dikwijls gemonteerd op een drager (de Nutsvoorzieningknoopcontainter). Bvb inspectieluik, hydrant, splitter, meter, pomp etc."
      },
      "equivalent": [],
      "parents": [
        "https://data.vlaanderen.be/ns/nutsvoorzieningen#Nutsvoorzieningknoop"
      ]
    },
    {
      "uri": "https://data.vlaanderen.be/ns/nutsvoorzieningen#TopografischElement",
      "name": "TopografischElement",
      "label": {
        "fr": "Enter your translation here",
        "nl": "Topografisch Element"
      },
      "sort": "Enter your translation here",
      "description": {
        "fr": "Enter your translation here",
        "nl": "Onderdeel van de beschrijving van vorm en kenmerken van het aardoppervlak."
      },
      "usage": {
        "fr": "Enter your translation here",
        "nl": "Typische elementen zijn relief, landvormen, waterlichamen, vegetatie"
      },
      "equivalent": [],
      "parents": []
    },
    {
      "uri": "https://data.vlaanderen.be/ns/nutsvoorzieningen#Toren",
      "name": "Toren",
      "label": {
        "fr": "Enter your translation here",
        "nl": "Toren"
      },
      "sort": "Enter your translation here",
      "description": {
        "fr": "Enter your translation here",
        "nl": "Eenvoudige Nutsvoorzieningknoopcontainer die de vorm aanneemt van een Toren."
      },
      "usage": {
        "fr": "Enter your translation here",
        "nl": "Typisch drager van monteerbaar Toebehoren en Kabels."
      },
      "equivalent": [],
      "parents": [
        "https://data.vlaanderen.be/ns/nutsvoorzieningen#Nutsvoorzieningknoopcontainer"
      ]
    },
    {
      "uri": "https://data.vlaanderen.be/ns/nutsvoorzieningen#Uiterlijk",
      "name": "Uiterlijk",
      "label": {
        "fr": "Enter your translation here",
        "nl": "Uiterlijk"
      },
      "sort": "Enter your translation here",
      "description": {
        "fr": "Enter your translation here",
        "nl": "De manier waarop een object eruit ziet."
      },
      "usage": {},
      "equivalent": [],
      "parents": []
    },
    {
      "uri": "https://data.vlaanderen.be/ns/nutsvoorzieningen#VerticalePositie",
      "name": "Verticalepositie",
      "label": {
        "fr": "Enter your translation here",
        "nl": "VerticalePositie"
      },
      "sort": "Enter your translation here",
      "description": {
        "fr": "Enter your translation here",
        "nl": "Positie in verticale richting tov een Referentieoppervlak."
      },
      "usage": {},
      "equivalent": [],
      "parents": []
    },
    {
      "uri": "https://data.vlaanderen.be/ns/nutsvoorzieningen#Waterleiding",
      "name": "Waterleiding",
      "label": {
        "fr": "Enter your translation here",
        "nl": "Waterleiding"
      },
      "sort": "Enter your translation here",
      "description": {
        "fr": "Enter your translation here",
        "nl": "Een Pijp die wordt gebruikt om water van de ene locatie naar de andere te transporteren."
      },
      "usage": {},
      "equivalent": [],
      "parents": [
        "https://data.vlaanderen.be/ns/nutsvoorzieningen#Pijp"
      ]
    }
  ],
  "properties": [
    {
      "uri": "https://data.vlaanderen.be/ns/nutsvoorzieningen#werkspanning",
      "name": "werkspanning",
      "label": {
        "fr": "Enter your translation here",
        "nl": "werkspanning"
      },
      "sort": "Enter your translation here",
      "description": {
        "fr": "Enter your translation here",
        "nl": "Spanning tijdens belasting."
      },
      "usage": {},
      "domain": [
        "https://data.vlaanderen.be/ns/nutsvoorzieningen#Electriciteitskabel"
      ],
      "range": [
        "http://def.isotc211.org/iso19103/2015/MeasureTypes#Measure"
      ],
      "parents": []
    },
    {
      "uri": "https://data.vlaanderen.be/ns/nutsvoorzieningen#watertype",
      "name": "watertype",
      "label": {
        "fr": "Enter your translation here",
        "nl": "watertype"
      },
      "sort": "Enter your translation here",
      "description": {
        "fr": "Enter your translation here",
        "nl": "Type van het water."
      },
      "usage": {},
      "domain": [
        "https://data.vlaanderen.be/ns/nutsvoorzieningen#Waterleiding"
      ],
      "range": [
        "http://www.w3.org/2004/02/skos/core#Concept"
      ],
      "parents": []
    },
    {
      "uri": "https://data.vlaanderen.be/ns/nutsvoorzieningen#waarschuwingstype",
      "name": "waarschuwingstype",
      "label": {
        "fr": "Enter your translation here",
        "nl": "waarschuwingstype"
      },
      "sort": "Enter your translation here",
      "description": {
        "fr": "Enter your translation here",
        "nl": "Manier waarop voor de aanwezigheid van de Linkset wordt gewaarschuwd."
      },
      "usage": {
        "fr": "Enter your translation here",
        "nl": "Bvb een bovengronds signalisatiebord om een ondergrondse gasleiding aan te duiden."
      },
      "domain": [
        "https://data.vlaanderen.be/ns/nutsvoorzieningen#Nutsvoorzieninglinkset"
      ],
      "range": [
        "http://www.w3.org/2004/02/skos/core#Concept"
      ],
      "parents": []
    },
    {
      "uri": "https://data.vlaanderen.be/ns/nutsvoorzieningen#verticalePositiedetail",
      "name": "verticalepositiedetail",
      "label": {
        "fr": "Enter your translation here",
        "nl": "verticalePositiedetail"
      },
      "sort": "Enter your translation here",
      "description": {
        "fr": "Enter your translation here",
        "nl": "Detail van de VerticalePositie van het element."
      },
      "usage": {
        "fr": "Enter your translation here",
        "nl": "Bv diepte."
      },
      "domain": [
        "https://data.vlaanderen.be/ns/nutsvoorzieningen#Nutsvoorzieningnetwerkelement"
      ],
      "range": [
        "https://data.vlaanderen.be/ns/nutsvoorzieningen#VerticalePositie"
      ],
      "parents": []
    },
    {
      "uri": "https://data.vlaanderen.be/ns/nutsvoorzieningen#torenhoogte",
      "name": "torenhoogte",
      "label": {
        "fr": "Enter your translation here",
        "nl": "torenhoogte"
      },
      "sort": "Enter your translation here",
      "description": {
        "fr": "Enter your translation here",
        "nl": "Hoogte van de Toren."
      },
      "usage": {},
      "domain": [
        "https://data.vlaanderen.be/ns/nutsvoorzieningen#Toren"
      ],
      "range": [
        "http://def.isotc211.org/iso19103/2015/MeasureTypes#Length"
      ],
      "parents": []
    },
    {
      "uri": "https://data.vlaanderen.be/ns/nutsvoorzieningen#thermischProducttype",
      "name": "thermischproducttype",
      "label": {
        "fr": "Enter your translation here",
        "nl": "thermischProducttype"
      },
      "sort": "Enter your translation here",
      "description": {
        "fr": "Enter your translation here",
        "nl": "Het type thermisch product dat door de ThermischePijp wordt getransporteerd."
      },
      "usage": {},
      "domain": [
        "https://data.vlaanderen.be/ns/nutsvoorzieningen#ThermischePijp"
      ],
      "range": [
        "http://www.w3.org/2004/02/skos/core#Concept"
      ],
      "parents": []
    },
    {
      "uri": "https://data.vlaanderen.be/ns/nutsvoorzieningen#temperatuur",
      "name": "temperatuur",
      "label": {
        "fr": "Enter your translation here",
        "nl": "temperatuur"
      },
      "sort": "Enter your translation here",
      "description": {
        "fr": "Enter your translation here",
        "nl": "De maximum toelaatbare temperatuur van de inhoud van de Pijp."
      },
      "usage": {},
      "domain": [
        "https://data.vlaanderen.be/ns/nutsvoorzieningen#ThermischePijp"
      ],
      "range": [
        "http://def.isotc211.org/iso19103/2015/MeasureTypes#Measure"
      ],
      "parents": []
    },
    {
      "uri": "https://data.vlaanderen.be/ns/nutsvoorzieningen#telecommunicatiekabelmateriaaltype",
      "name": "telecommunicatiekabelmateriaaltype",
      "label": {
        "fr": "Enter your translation here",
        "nl": "telecommunicatiekabelmateriaaltype"
      },
      "sort": "Enter your translation here",
      "description": {
        "fr": "Enter your translation here",
        "nl": "Type van kabelmateriaal."
      },
      "usage": {},
      "domain": [
        "https://data.vlaanderen.be/ns/nutsvoorzieningen#Telecommunicatiekabel"
      ],
      "range": [
        "http://www.w3.org/2004/02/skos/core#Concept"
      ],
      "parents": []
    },
    {
      "uri": "https://data.vlaanderen.be/ns/nutsvoorzieningen#tekst",
      "name": "tekst",
      "label": {
        "fr": "Enter your translation here",
        "nl": "tekst"
      },
      "sort": "Enter your translation here",
      "description": {
        "fr": "Enter your translation here",
        "nl": "Tekst van de Annotatie."
      },
      "usage": {
        "fr": "Enter your translation here",
        "nl": "Bvb de maat in het geval van een Maataanduiding."
      },
      "domain": [
        "https://data.vlaanderen.be/ns/nutsvoorzieningen#Annotatie"
      ],
      "range": [
        "http://www.w3.org/1999/02/22-rdf-syntax-ns#langString"
      ],
      "parents": []
    },
    {
      "uri": "https://data.vlaanderen.be/ns/nutsvoorzieningen#technischeSpecificate",
      "name": "technischespecificatie",
      "label": {
        "fr": "Enter your translation here",
        "nl": "technischeSpecificatie"
      },
      "sort": "Enter your translation here",
      "description": {
        "fr": "Enter your translation here",
        "nl": "Nadere bepaling van de linkset."
      },
      "usage": {
        "fr": "Enter your translation here",
        "nl": "Bv diameter, materiaal etc. Bvb PE200 om polyethyleenbuis van 200mm diameter te specifiëren."
      },
      "domain": [
        "https://data.vlaanderen.be/ns/nutsvoorzieningen#Nutsvoorzieninglinkset"
      ],
      "range": [
        "http://www.w3.org/1999/02/22-rdf-syntax-ns#langString"
      ],
      "parents": []
    },
    {
      "uri": "https://data.vlaanderen.be/ns/nutsvoorzieningen#standaardVerticalePositiedetail",
      "name": "standaardverticalepositiedetail",
      "label": {
        "fr": "Enter your translation here",
        "nl": "standaardVerticalePositiedetail"
      },
      "sort": "Enter your translation here",
      "description": {
        "fr": "Enter your translation here",
        "nl": "Standaard VerticalePositie van elementen in het netwerk."
      },
      "usage": {
        "fr": "Enter your translation here",
        "nl": "Bv de standaard Diepte waarop de elementen zich bevinden."
      },
      "domain": [
        "https://data.vlaanderen.be/ns/nutsvoorzieningen#Nutsvoorzieningnetwerk"
      ],
      "range": [
        "https://data.vlaanderen.be/ns/nutsvoorzieningen#VerticalePositie"
      ],
      "parents": []
    },
    {
      "uri": "https://data.vlaanderen.be/ns/nutsvoorzieningen#rotatiehoek",
      "name": "rotatiehoek",
      "label": {
        "fr": "Enter your translation here",
        "nl": "rotatiehoek"
      },
      "sort": "Enter your translation here",
      "description": {
        "fr": "Enter your translation here",
        "nl": "Hoek waarmee de Annotatie bij weergave moet worden geroteerd."
      },
      "usage": {
        "fr": "Enter your translation here",
        "nl": "Typisch om de Annotatie te aligneren met het Object waarop het betrekking heeft, bvb evenwijdig met de kabel."
      },
      "domain": [
        "https://data.vlaanderen.be/ns/nutsvoorzieningen#Annotatie"
      ],
      "range": [
        "http://def.isotc211.org/iso19103/2015/MeasureTypes#Measure"
      ],
      "parents": []
    },
    {
      "uri": "https://data.vlaanderen.be/ns/nutsvoorzieningen#rioolwatertype",
      "name": "rioolwatertype",
      "label": {
        "fr": "Enter your translation here",
        "nl": "rioolwatertype"
      },
      "sort": "Enter your translation here",
      "description": {
        "fr": "Enter your translation here",
        "nl": "Type van rioolwater."
      },
      "usage": {},
      "domain": [
        "https://data.vlaanderen.be/ns/nutsvoorzieningen#Rioolpijp"
      ],
      "range": [
        "http://www.w3.org/2004/02/skos/core#Concept"
      ],
      "parents": []
    },
    {
      "uri": "https://data.vlaanderen.be/ns/nutsvoorzieningen#referentieOppervlak",
      "name": "referentieoppervlak",
      "label": {
        "fr": "Enter your translation here",
        "nl": "referentieOppervlak"
      },
      "sort": "Enter your translation here",
      "description": {
        "fr": "Enter your translation here",
        "nl": "Verwijzing naar het Referentieoppervlak."
      },
      "usage": {
        "fr": "Enter your translation here",
        "nl": "Bvb het maaiveld."
      },
      "domain": [
        "https://data.vlaanderen.be/ns/nutsvoorzieningen#VerticalePositie"
      ],
      "range": [
        "https://data.vlaanderen.be/ns/nutsvoorzieningen#Referentieoppervlak"
      ],
      "parents": []
    },
    {
      "uri": "https://data.vlaanderen.be/ns/nutsvoorzieningen#pijpdiameter",
      "name": "pijpdiameter",
      "label": {
        "fr": "Enter your translation here",
        "nl": "pijpdiameter"
      },
      "sort": "Enter your translation here",
      "description": {
        "fr": "Enter your translation here",
        "nl": "Buitendiameter van de Pijp."
      },
      "usage": {},
      "domain": [
        "https://data.vlaanderen.be/ns/nutsvoorzieningen#Pijp"
      ],
      "range": [
        "http://def.isotc211.org/iso19103/2015/MeasureTypes#Measure"
      ],
      "parents": []
    },
    {
      "uri": "https://data.vlaanderen.be/ns/nutsvoorzieningen#paalhoogte",
      "name": "paalhoogte",
      "label": {
        "fr": "Enter your translation here",
        "nl": "paalhoogte"
      },
      "sort": "Enter your translation here",
      "description": {
        "fr": "Enter your translation here",
        "nl": "Hoogte van de Paal."
      },
      "usage": {},
      "domain": [
        "https://data.vlaanderen.be/ns/nutsvoorzieningen#Paal"
      ],
      "range": [
        "http://def.isotc211.org/iso19103/2015/MeasureTypes#Length"
      ],
      "parents": []
    },
    {
      "uri": "https://data.vlaanderen.be/ns/nutsvoorzieningen#olieGasChemicalienProducttype",
      "name": "oliegaschemicaliënproducttype",
      "label": {
        "fr": "Enter your translation here",
        "nl": "olieGasChemicaliënProducttype"
      },
      "sort": "Enter your translation here",
      "description": {
        "fr": "Enter your translation here",
        "nl": "Het type olie-, gas- of chemisch product dat door de olie-, gas- of chemische pijp wordt getransporteerd."
      },
      "usage": {},
      "domain": [
        "https://data.vlaanderen.be/ns/nutsvoorzieningen#OlieGasChemicalienPijp"
      ],
      "range": [
        "http://www.w3.org/2004/02/skos/core#Concept"
      ],
      "parents": []
    },
    {
      "uri": "https://data.vlaanderen.be/ns/nutsvoorzieningen#nutsvoorzieningleveringstype",
      "name": "nutsvoorzieningleveringstype",
      "label": {
        "fr": "Enter your translation here",
        "nl": "nutsvoorzieningleveringstype"
      },
      "sort": "Enter your translation here",
      "description": {
        "fr": "Enter your translation here",
        "nl": "Manier waarop de nutsvoorziening wordt geleverd."
      },
      "usage": {
        "fr": "Enter your translation here",
        "nl": "Bvb transport, distributie, collectie. Resp bvb van gas, elektriciteit, afvalwater."
      },
      "domain": [
        "https://data.vlaanderen.be/ns/nutsvoorzieningen#Nutsvoorzieninglinkset"
      ],
      "range": [
        "http://www.w3.org/2004/02/skos/core#Concept"
      ],
      "parents": []
    },
    {
      "uri": "https://data.vlaanderen.be/ns/nutsvoorzieningen#nominaleSpanning",
      "name": "nominaleSpanning",
      "label": {
        "fr": "Enter your translation here",
        "nl": "nominale Spanning"
      },
      "sort": "Enter your translation here",
      "description": {
        "fr": "Enter your translation here",
        "nl": "Spanning zonder belasting."
      },
      "usage": {},
      "domain": [
        "https://data.vlaanderen.be/ns/nutsvoorzieningen#Electriciteitskabel"
      ],
      "range": [
        "http://def.isotc211.org/iso19103/2015/MeasureTypes#Measure"
      ],
      "parents": []
    },
    {
      "uri": "https://data.vlaanderen.be/ns/nutsvoorzieningen#netwerk",
      "name": "netwerk",
      "label": {
        "fr": "Enter your translation here",
        "nl": "netwerk"
      },
      "sort": "Enter your translation here",
      "description": {
        "fr": "Enter your translation here",
        "nl": "Nutsvoorzieningnetwerk dat met het Nutsvoorzieningnetwerk is geassocieerd."
      },
      "usage": {
        "fr": "Enter your translation here",
        "nl": "Bvb een deelnetwerk."
      },
      "domain": [
        "https://data.vlaanderen.be/ns/nutsvoorzieningen#Nutsvoorzieningnetwerk"
      ],
      "range": [
        "https://data.vlaanderen.be/ns/nutsvoorzieningen#Nutsvoorzieningnetwerk"
      ],
      "parents": []
    },
    {
      "uri": "https://data.vlaanderen.be/ns/nutsvoorzieningen#nauwkeurigheid",
      "name": "nauwkeurigheid",
      "label": {
        "fr": "Enter your translation here",
        "nl": "nauwkeurigheid"
      },
      "sort": "Enter your translation here",
      "description": {
        "fr": "Enter your translation here",
        "nl": "De PositioneleNauwkeurigheid van de Opmeting."
      },
      "usage": {},
      "domain": [
        "https://data.vlaanderen.be/ns/generiek#Opmeting"
      ],
      "range": [
        "http://def.isotc211.org/iso19157/2013/DataQuality_2#DQ_PositionalAccuracy"
      ],
      "parents": []
    },
    {
      "uri": "https://data.vlaanderen.be/ns/nutsvoorzieningen#materiaaltype",
      "name": "materiaaltype",
      "label": {
        "fr": "Enter your translation here",
        "nl": "materiaaltype"
      },
      "sort": "Enter your translation here",
      "description": {
        "fr": "Enter your translation here",
        "nl": "Soort materiaal waaruit de Linkset bestaat."
      },
      "usage": {},
      "domain": [
        "https://data.vlaanderen.be/ns/nutsvoorzieningen#Nutsvoorzieninglinkset"
      ],
      "range": [
        "http://www.w3.org/2004/02/skos/core#Concept"
      ],
      "parents": []
    },
    {
      "uri": "https://data.vlaanderen.be/ns/nutsvoorzieningen#knoop",
      "name": "knoop",
      "label": {
        "fr": "Enter your translation here",
        "nl": "knoop"
      },
      "sort": "Enter your translation here",
      "description": {
        "fr": "Enter your translation here",
        "nl": "Nutsvoorzieningknoop die de Nutsvoorzieningknoopcontainer omvat."
      },
      "usage": {},
      "domain": [
        "https://data.vlaanderen.be/ns/nutsvoorzieningen#Nutsvoorzieningknoopcontainer"
      ],
      "range": [
        "https://data.vlaanderen.be/ns/nutsvoorzieningen#Nutsvoorzieningknoop"
      ],
      "parents": []
    },
    {
      "uri": "https://data.vlaanderen.be/ns/nutsvoorzieningen#kleur",
      "name": "kleur",
      "label": {
        "fr": "Enter your translation here",
        "nl": "kleur"
      },
      "sort": "Enter your translation here",
      "description": {
        "fr": "Enter your translation here",
        "nl": "De kleur van het object."
      },
      "usage": {},
      "domain": [
        "https://data.vlaanderen.be/ns/nutsvoorzieningen#Uiterlijk"
      ],
      "range": [
        "http://www.w3.org/2004/02/skos/core#Concept"
      ],
      "parents": []
    },
    {
      "uri": "https://data.vlaanderen.be/ns/nutsvoorzieningen#kanaalbreedte",
      "name": "kanaalbreedte",
      "label": {
        "fr": "Enter your translation here",
        "nl": "kanaalbreedte"
      },
      "sort": "Enter your translation here",
      "description": {
        "fr": "Enter your translation here",
        "nl": "Breedte van het Kanaal"
      },
      "usage": {},
      "domain": [
        "https://data.vlaanderen.be/ns/nutsvoorzieningen#Kanaal"
      ],
      "range": [
        "http://def.isotc211.org/iso19103/2015/MeasureTypes#Length"
      ],
      "parents": []
    },
    {
      "uri": "https://data.vlaanderen.be/ns/nutsvoorzieningen#kabeldiameter",
      "name": "kabeldiameter",
      "label": {
        "fr": "Enter your translation here",
        "nl": "kabeldiameter"
      },
      "sort": "Enter your translation here",
      "description": {
        "fr": "Enter your translation here",
        "nl": "Diameter van de kabel."
      },
      "usage": {},
      "domain": [
        "https://data.vlaanderen.be/ns/nutsvoorzieningen#Kabel"
      ],
      "range": [
        "http://def.isotc211.org/iso19103/2015/MeasureTypes#Measure"
      ],
      "parents": []
    },
    {
      "uri": "https://data.vlaanderen.be/ns/nutsvoorzieningen#huidigeStatus",
      "name": "huidigestatus",
      "label": {
        "fr": "Enter your translation here",
        "nl": "huidigeStatus"
      },
      "sort": "Enter your translation here",
      "description": {
        "fr": "Enter your translation here",
        "nl": "De status van het element met betrekking tot de voltooiing en het gebruik ervan."
      },
      "usage": {},
      "domain": [
        "https://data.vlaanderen.be/ns/nutsvoorzieningen#Nutsvoorzieningnetwerkelement"
      ],
      "range": [
        "http://www.w3.org/2004/02/skos/core#Concept"
      ],
      "parents": []
    },
    {
      "uri": "https://data.vlaanderen.be/ns/nutsvoorzieningen#geldigVan",
      "name": "geldigvan",
      "label": {
        "fr": "Enter your translation here",
        "nl": "geldigVan"
      },
      "sort": "Enter your translation here",
      "description": {
        "fr": "Enter your translation here",
        "nl": "Tijdstip vanaf wanneer het element in de werkelijkheid bestond."
      },
      "usage": {},
      "domain": [
        "https://data.vlaanderen.be/ns/nutsvoorzieningen#Nutsvoorzieningnetwerkelement"
      ],
      "range": [
        "http://www.w3.org/2001/XMLSchema#dateTime"
      ],
      "parents": []
    },
    {
      "uri": "https://data.vlaanderen.be/ns/nutsvoorzieningen#geldigTot",
      "name": "geldigtot",
      "label": {
        "fr": "Enter your translation here",
        "nl": "geldigTot"
      },
      "sort": "Enter your translation here",
      "description": {
        "fr": "Enter your translation here",
        "nl": "Tijdstip tot wanneer het element in de werkelijkheid bestond."
      },
      "usage": {},
      "domain": [
        "https://data.vlaanderen.be/ns/nutsvoorzieningen#Nutsvoorzieningnetwerkelement"
      ],
      "range": [
        "http://www.w3.org/2001/XMLSchema#dateTime"
      ],
      "parents": []
    },
    {
      "uri": "https://data.vlaanderen.be/ns/nutsvoorzieningen#geheel",
      "name": "geheel",
      "label": {
        "fr": "Enter your translation here",
        "nl": "geheel"
      },
      "sort": "Enter your translation here",
      "description": {
        "fr": "Enter your translation here",
        "nl": "Annotatie waarvan de Annotatie deel uitmaakt."
      },
      "usage": {
        "fr": "Enter your translation here",
        "nl": "Bvb de Maataanduiding waartoe de maatvoeringslijn behoort."
      },
      "domain": [
        "https://data.vlaanderen.be/ns/nutsvoorzieningen#Annotatie"
      ],
      "range": [
        "https://data.vlaanderen.be/ns/nutsvoorzieningen#Annotatie"
      ],
      "parents": []
    },
    {
      "uri": "https://data.vlaanderen.be/ns/nutsvoorzieningen#geassocieerdMet",
      "name": "geassocieerdMet",
      "label": {
        "fr": "Enter your translation here",
        "nl": "geassocieerd met"
      },
      "sort": "Enter your translation here",
      "description": {
        "fr": "Enter your translation here",
        "nl": "Object waar de Annotatie betrekking op heeft"
      },
      "usage": {
        "fr": "Enter your translation here",
        "nl": "Bvb een kabel."
      },
      "domain": [
        "https://data.vlaanderen.be/ns/nutsvoorzieningen#Annotatie"
      ],
      "range": [
        "http://www.w3.org/ns/prov#Entity"
      ],
      "parents": []
    },
    {
      "uri": "https://data.vlaanderen.be/ns/nutsvoorzieningen#functie",
      "name": "functie",
      "label": {
        "fr": "Enter your translation here",
        "nl": "functie"
      },
      "sort": "Enter your translation here",
      "description": {
        "fr": "Enter your translation here",
        "nl": "Activiteiten uitgevoerd door het complex."
      },
      "usage": {
        "fr": "Enter your translation here",
        "nl": "Eventueel aangevuld met informatie over inputs en outputs van de activiteiten."
      },
      "domain": [
        "https://data.vlaanderen.be/ns/generiek#Activiteitencomplex"
      ],
      "range": [
        "https://data.vlaanderen.be/ns/generiek#Functie"
      ],
      "parents": []
    },
    {
      "uri": "https://data.vlaanderen.be/ns/nutsvoorzieningen#element",
      "name": "element",
      "label": {
        "fr": "Enter your translation here",
        "nl": "element"
      },
      "sort": "Enter your translation here",
      "description": {
        "fr": "Enter your translation here",
        "nl": "Nutsvoorzieningnetwerkelement dat tot het netwerk behoort."
      },
      "usage": {},
      "domain": [
        "https://data.vlaanderen.be/ns/nutsvoorzieningen#Nutsvoorzieningnetwerk"
      ],
      "range": [
        "https://data.vlaanderen.be/ns/nutsvoorzieningen#Nutsvoorzieningnetwerkelement"
      ],
      "parents": []
    },
    {
      "uri": "https://data.vlaanderen.be/ns/nutsvoorzieningen#druk",
      "name": "druk",
      "label": {
        "fr": "Enter your translation here",
        "nl": "druk"
      },
      "sort": "Enter your translation here",
      "description": {
        "fr": "Enter your translation here",
        "nl": "De maximaal toegestane operationele druk waarbij een product door een Pijp wordt getransporteerd."
      },
      "usage": {},
      "domain": [
        "https://data.vlaanderen.be/ns/nutsvoorzieningen#Pijp"
      ],
      "range": [
        "http://def.isotc211.org/iso19103/2015/MeasureTypes#Measure"
      ],
      "parents": []
    },
    {
      "uri": "https://data.vlaanderen.be/ns/nutsvoorzieningen#documentatie",
      "name": "documentatie",
      "label": {
        "fr": "Enter your translation here",
        "nl": "documentatie"
      },
      "sort": "Enter your translation here",
      "description": {
        "fr": "Enter your translation here",
        "nl": "Verwijzing naar een Document met extra informatie over het complex."
      },
      "usage": {},
      "domain": [
        "https://data.vlaanderen.be/ns/generiek#Activiteitencomplex"
      ],
      "range": [
        "http://xmlns.com/foaf/0.1/Document"
      ],
      "parents": []
    },
    {
      "uri": "https://data.vlaanderen.be/ns/nutsvoorzieningen#disclaimer",
      "name": "disclaimer",
      "label": {
        "fr": "Enter your translation here",
        "nl": "disclaimer"
      },
      "sort": "Enter your translation here",
      "description": {
        "fr": "Enter your translation here",
        "nl": "Wettelijke tekst waarin vertrouwelijkheidsclausules worden beschreven die van toepassing zijn op de informatie over het nutsnetwerk."
      },
      "usage": {},
      "domain": [
        "https://data.vlaanderen.be/ns/nutsvoorzieningen#Nutsvoorzieningnetwerk"
      ],
      "range": [
        "http://www.w3.org/1999/02/22-rdf-syntax-ns#langString"
      ],
      "parents": []
    },
    {
      "uri": "https://data.vlaanderen.be/ns/nutsvoorzieningen#diepte",
      "name": "diepte",
      "label": {
        "fr": "Enter your translation here",
        "nl": "diepte"
      },
      "sort": "Enter your translation here",
      "description": {
        "fr": "Enter your translation here",
        "nl": "Afstand onder het Referentieoppervlak."
      },
      "usage": {},
      "domain": [
        "https://data.vlaanderen.be/ns/nutsvoorzieningen#Diepte"
      ],
      "range": [
        "http://def.isotc211.org/iso19103/2015/MeasureTypes#Measure"
      ],
      "parents": []
    },
    {
      "uri": "https://data.vlaanderen.be/ns/nutsvoorzieningen#deel",
      "name": "deel",
      "label": {
        "fr": "Enter your translation here",
        "nl": "deel"
      },
      "sort": "Enter your translation here",
      "description": {
        "fr": "Enter your translation here",
        "nl": "Annotatie die deel uitmaakt van de Annotatie."
      },
      "usage": {
        "fr": "Enter your translation here",
        "nl": "Bvb de maatvoeringslijn in het geval van een Maataanduiding bestaande uit twee pijlen en een maatvoeringshulplijn."
      },
      "domain": [
        "https://data.vlaanderen.be/ns/nutsvoorzieningen#Annotatie"
      ],
      "range": [
        "https://data.vlaanderen.be/ns/nutsvoorzieningen#Annotatie"
      ],
      "parents": []
    },
    {
      "uri": "https://data.vlaanderen.be/ns/nutsvoorzieningen#bevoegdePartij",
      "name": "bevoegdepartij",
      "label": {
        "fr": "Enter your translation here",
        "nl": "bevoegdePartij"
      },
      "sort": "Enter your translation here",
      "description": {
        "fr": "Enter your translation here",
        "nl": "Partijen die bevoegd zijn om het Nutsvoorzieningnetwerk te beheren, exploiteren of er eigenaar van is."
      },
      "usage": {},
      "domain": [
        "https://data.vlaanderen.be/ns/nutsvoorzieningen#Nutsvoorzieningnetwerk"
      ],
      "range": [
        "http://purl.org/dc/terms/Agent"
      ],
      "parents": []
    },
    {
      "uri": "https://data.vlaanderen.be/ns/nutsvoorzieningen#afstand",
      "name": "afstand",
      "label": {
        "fr": "Enter your translation here",
        "nl": "afstand"
      },
      "sort": "Enter your translation here",
      "description": {
        "fr": "Enter your translation here",
        "nl": "De VerticalePositie als afstand tov het Referentieoppervlak."
      },
      "usage": {
        "fr": "Enter your translation here",
        "nl": "Bvb de afstand tov het maaiveld."
      },
      "domain": [
        "https://data.vlaanderen.be/ns/nutsvoorzieningen#VerticalePositie"
      ],
      "range": [
        "http://def.isotc211.org/iso19103/2015/MeasureTypes#Measure"
      ],
      "parents": []
    },
    {
      "uri": "https://data.vlaanderen.be/ns/nutsvoorzieningen#adres",
      "name": "adres",
      "label": {
        "fr": "Enter your translation here",
        "nl": "adres"
      },
      "sort": "Enter your translation here",
      "description": {
        "fr": "Enter your translation here",
        "nl": "Adres van de aansluiting."
      },
      "usage": {},
      "domain": [
        "https://data.vlaanderen.be/ns/nutsvoorzieningen#Aansluiting"
      ],
      "range": [
        "http://www.w3.org/ns/locn#Address"
      ],
      "parents": []
    },
    {
      "uri": "https://data.vlaanderen.be/ns/nutsvoorzieningen#activiteitencomplexreferentie",
      "name": "activiteitencomplexreferentie",
      "label": {
        "fr": "Enter your translation here",
        "nl": "activiteitencomplexreferentie"
      },
      "sort": "Enter your translation here",
      "description": {
        "fr": "Enter your translation here",
        "nl": "Activiteitencomplex dat tot het netwerk behoort."
      },
      "usage": {},
      "domain": [
        "https://data.vlaanderen.be/ns/nutsvoorzieningen#Nutsvoorzieningnetwerk"
      ],
      "range": [
        "https://data.vlaanderen.be/ns/generiek#Activiteitencomplex"
      ],
      "parents": []
    },
    {
      "uri": "https://data.vlaanderen.be/ns/nutsvoorzieningen#^identificator",
      "name": "identificator",
      "label": {
        "fr": "Enter your translation here",
        "nl": "identificator"
      },
      "sort": "Enter your translation here",
      "description": {
        "fr": "Enter your translation here",
        "nl": "Identificator van het element."
      },
      "usage": {},
      "domain": [
        "https://data.vlaanderen.be/ns/nutsvoorzieningen#Nutsvoorzieningnetwerkelement"
      ],
      "range": [
        "http://www.w3.org/ns/adms#Identifier"
      ],
      "parents": []
    },
    {
      "uri": "https://data.vlaanderen.be/ns/nutsvoorzieningen#^geografischeNaam",
      "name": "geografischenaam",
      "label": {
        "fr": "Enter your translation here",
        "nl": "geografischeNaam"
      },
      "sort": "Enter your translation here",
      "description": {
        "fr": "Enter your translation here",
        "nl": "Naam waaronder het netwerk bekend staat."
      },
      "usage": {},
      "domain": [
        "https://data.vlaanderen.be/ns/nutsvoorzieningen#Nutsvoorzieningnetwerk"
      ],
      "range": [
        "http://www.w3.org/1999/02/22-rdf-syntax-ns#langString"
      ],
      "parents": []
    },
    {
      "uri": "https://data.vlaanderen.be/ns/nutsvoorzieningen#VerticalePositie.verticalePositie",
      "name": "verticalepositie",
      "label": {
        "fr": "Enter your translation here",
        "nl": "verticalePositie"
      },
      "sort": "Enter your translation here",
      "description": {
        "fr": "Enter your translation here",
        "nl": "De VerticalePositie als positie in een verticaal coördinaatsysteem."
      },
      "usage": {
        "fr": "Enter your translation here",
        "nl": "Bvb in België de z-coördinaat in TAW."
      },
      "domain": [
        "https://data.vlaanderen.be/ns/nutsvoorzieningen#VerticalePositie"
      ],
      "range": [
        "https://data.vlaanderen.be/ns/generiek#DirectePositie"
      ],
      "parents": []
    },
    {
      "uri": "https://data.vlaanderen.be/ns/nutsvoorzieningen#Referentieoppervlak.verticalePositie",
      "name": "verticalepositie",
      "label": {
        "fr": "Enter your translation here",
        "nl": "verticalePositie"
      },
      "sort": "Enter your translation here",
      "description": {
        "fr": "Enter your translation here",
        "nl": "De VerticalePositie van het Referentieoppervlak als positie in een verticaal coördinaatsysteem."
      },
      "usage": {
        "fr": "Enter your translation here",
        "nl": "Bvb in België de z-coördinaat in TAW."
      },
      "domain": [
        "https://data.vlaanderen.be/ns/nutsvoorzieningen#Referentieoppervlak"
      ],
      "range": [
        "https://data.vlaanderen.be/ns/generiek#DirectePositie"
      ],
      "parents": []
    },
    {
      "uri": "https://data.vlaanderen.be/ns/nutsvoorzieningen#Pijp.subthema",
      "name": "subthema",
      "label": {
        "fr": "Enter your translation here",
        "nl": "subthema"
      },
      "sort": "Enter your translation here",
      "description": {
        "fr": "Enter your translation here",
        "nl": "Classificatie van de Pijp volgens het thematisch domein waartoe deze behoort."
      },
      "usage": {},
      "domain": [
        "https://data.vlaanderen.be/ns/nutsvoorzieningen#Pijp"
      ],
      "range": [
        "http://www.w3.org/2004/02/skos/core#Concept"
      ],
      "parents": []
    },
    {
      "uri": "https://data.vlaanderen.be/ns/nutsvoorzieningen#Pijp.pijp",
      "name": "pijp",
      "label": {
        "fr": "Enter your translation here",
        "nl": "pijp"
      },
      "sort": "Enter your translation here",
      "description": {
        "fr": "Enter your translation here",
        "nl": "Andere Pijp gelegen in de Pijp."
      },
      "usage": {},
      "domain": [
        "https://data.vlaanderen.be/ns/nutsvoorzieningen#Pijp"
      ],
      "range": [
        "https://data.vlaanderen.be/ns/nutsvoorzieningen#Pijp"
      ],
      "parents": []
    },
    {
      "uri": "https://data.vlaanderen.be/ns/nutsvoorzieningen#Pijp.kabel",
      "name": "kabel",
      "label": {
        "fr": "Enter your translation here",
        "nl": "kabel"
      },
      "sort": "Enter your translation here",
      "description": {
        "fr": "Enter your translation here",
        "nl": "Kabel gelegen in de Pijp."
      },
      "usage": {},
      "domain": [
        "https://data.vlaanderen.be/ns/nutsvoorzieningen#Pijp"
      ],
      "range": [
        "https://data.vlaanderen.be/ns/nutsvoorzieningen#Kabel"
      ],
      "parents": []
    },
    {
      "uri": "https://data.vlaanderen.be/ns/nutsvoorzieningen#Opmeting.uitgevoerdDoor",
      "name": "uitgevoerddoor",
      "label": {
        "fr": "Enter your translation here",
        "nl": "uitgevoerdDoor"
      },
      "sort": "Enter your translation here",
      "description": {
        "fr": "Enter your translation here",
        "nl": "Agent die de Opmeting heeft uitgevoerd."
      },
      "usage": {},
      "domain": [
        "https://data.vlaanderen.be/ns/generiek#Opmeting"
      ],
      "range": [
        "http://purl.org/dc/terms/Agent"
      ],
      "parents": []
    },
    {
      "uri": "https://data.vlaanderen.be/ns/nutsvoorzieningen#Opmeting.methode",
      "name": "methode",
      "label": {
        "fr": "Enter your translation here",
        "nl": "methode"
      },
      "sort": "Enter your translation here",
      "description": {
        "fr": "Enter your translation here",
        "nl": "Aard van de gebruikte methode."
      },
      "usage": {},
      "domain": [
        "https://data.vlaanderen.be/ns/generiek#Opmeting"
      ],
      "range": [
        "http://www.w3.org/2004/02/skos/core#Concept"
      ],
      "parents": []
    },
    {
      "uri": "https://data.vlaanderen.be/ns/nutsvoorzieningen#Nutsvoorzieningnetwerkelement.verticalePositie",
      "name": "verticalepositie",
      "label": {
        "fr": "Enter your translation here",
        "nl": "verticalePositie"
      },
      "sort": "Enter your translation here",
      "description": {
        "fr": "Enter your translation here",
        "nl": "Algemene aanduiding van de VerticalePositie van het element."
      },
      "usage": {
        "fr": "Enter your translation here",
        "nl": "Bv ondergronds, bovengronds."
      },
      "domain": [
        "https://data.vlaanderen.be/ns/nutsvoorzieningen#Nutsvoorzieningnetwerkelement"
      ],
      "range": [
        "http://www.w3.org/2004/02/skos/core#Concept"
      ],
      "parents": []
    },
    {
      "uri": "https://data.vlaanderen.be/ns/nutsvoorzieningen#Nutsvoorzieningnetwerkelement.inNetwerk",
      "name": "innetwerk",
      "label": {
        "fr": "Enter your translation here",
        "nl": "inNetwerk"
      },
      "sort": "Enter your translation here",
      "description": {
        "fr": "Enter your translation here",
        "nl": "Nutsvoorzieningnetwerk waartoe het element behoort."
      },
      "usage": {},
      "domain": [
        "https://data.vlaanderen.be/ns/nutsvoorzieningen#Nutsvoorzieningnetwerkelement"
      ],
      "range": [
        "https://data.vlaanderen.be/ns/nutsvoorzieningen#Nutsvoorzieningnetwerk"
      ],
      "parents": []
    },
    {
      "uri": "https://data.vlaanderen.be/ns/nutsvoorzieningen#Nutsvoorzieninglinkset.zichtbaarheid",
      "name": "zichtbaarheid",
      "label": {
        "fr": "Enter your translation here",
        "nl": "zichtbaarheid"
      },
      "sort": "Enter your translation here",
      "description": {
        "fr": "Enter your translation here",
        "nl": "Mate waarin de container waarneembaar is."
      },
      "usage": {
        "fr": "Enter your translation here",
        "nl": "Bvb nietBovengrondsZichtbaar."
      },
      "domain": [
        "https://data.vlaanderen.be/ns/nutsvoorzieningen#Nutsvoorzieninglinkset"
      ],
      "range": [
        "http://www.w3.org/2004/02/skos/core#Concept"
      ],
      "parents": []
    },
    {
      "uri": "https://data.vlaanderen.be/ns/nutsvoorzieningen#Nutsvoorzieninglinkset.uiterlijk",
      "name": "uiterlijk",
      "label": {
        "fr": "Enter your translation here",
        "nl": "uiterlijk"
      },
      "sort": "Enter your translation here",
      "description": {
        "fr": "Enter your translation here",
        "nl": "Uitzicht van de Linkset."
      },
      "usage": {},
      "domain": [
        "https://data.vlaanderen.be/ns/nutsvoorzieningen#Nutsvoorzieninglinkset"
      ],
      "range": [
        "https://data.vlaanderen.be/ns/nutsvoorzieningen#Uiterlijk"
      ],
      "parents": []
    },
    {
      "uri": "https://data.vlaanderen.be/ns/nutsvoorzieningen#Nutsvoorzieninglinkset.risico",
      "name": "risico",
      "label": {
        "fr": "Enter your translation here",
        "nl": "risico"
      },
      "sort": "Enter your translation here",
      "description": {
        "fr": "Enter your translation here",
        "nl": "Geeft aan of de linkset als gevaarlijk kan beschouwd worden."
      },
      "usage": {},
      "domain": [
        "https://data.vlaanderen.be/ns/nutsvoorzieningen#Nutsvoorzieninglinkset"
      ],
      "range": [
        "http://www.w3.org/2004/02/skos/core#Concept"
      ],
      "parents": []
    },
    {
      "uri": "https://data.vlaanderen.be/ns/nutsvoorzieningen#Nutsvoorzieningknoopcontainer.zichtbaarheid",
      "name": "zichtbaarheid",
      "label": {
        "fr": "Enter your translation here",
        "nl": "zichtbaarheid"
      },
      "sort": "Enter your translation here",
      "description": {
        "fr": "Enter your translation here",
        "nl": "Mate waarin de container waarneembaar is."
      },
      "usage": {
        "fr": "Enter your translation here",
        "nl": "Bvb nietBovengrondsZichtbaar."
      },
      "domain": [
        "https://data.vlaanderen.be/ns/nutsvoorzieningen#Nutsvoorzieningknoopcontainer"
      ],
      "range": [
        "http://www.w3.org/2004/02/skos/core#Concept"
      ],
      "parents": []
    },
    {
      "uri": "https://data.vlaanderen.be/ns/nutsvoorzieningen#Nutsvoorzieningknoopcontainer.uiterlijk",
      "name": "uiterlijk",
      "label": {
        "fr": "Enter your translation here",
        "nl": "uiterlijk"
      },
      "sort": "Enter your translation here",
      "description": {
        "fr": "Enter your translation here",
        "nl": "Uitzicht van de container."
      },
      "usage": {
        "fr": "Enter your translation here",
        "nl": "Bvb de kleur."
      },
      "domain": [
        "https://data.vlaanderen.be/ns/nutsvoorzieningen#Nutsvoorzieningknoopcontainer"
      ],
      "range": [
        "https://data.vlaanderen.be/ns/nutsvoorzieningen#Uiterlijk"
      ],
      "parents": []
    },
    {
      "uri": "https://data.vlaanderen.be/ns/nutsvoorzieningen#Nutsvoorzieningknoopcontainer.risico",
      "name": "risico",
      "label": {
        "fr": "Enter your translation here",
        "nl": "risico"
      },
      "sort": "Enter your translation here",
      "description": {
        "fr": "Enter your translation here",
        "nl": "Geeft aan of de container als gevaarlijk kan beschouwd worden."
      },
      "usage": {},
      "domain": [
        "https://data.vlaanderen.be/ns/nutsvoorzieningen#Nutsvoorzieningknoopcontainer"
      ],
      "range": [
        "http://www.w3.org/2004/02/skos/core#Concept"
      ],
      "parents": []
    },
    {
      "uri": "https://data.vlaanderen.be/ns/nutsvoorzieningen#Nutsvoorzieningknoopcontainer.orientatie",
      "name": "oriëntatie",
      "label": {
        "fr": "Enter your translation here",
        "nl": "oriëntatie"
      },
      "sort": "Enter your translation here",
      "description": {
        "fr": "Enter your translation here",
        "nl": "Hoek waarmee het symbool dat de container weergeeft op kaart moet worden geroteerd."
      },
      "usage": {},
      "domain": [
        "https://data.vlaanderen.be/ns/nutsvoorzieningen#Nutsvoorzieningknoopcontainer"
      ],
      "range": [
        "http://def.isotc211.org/iso19103/2015/MeasureTypes#Measure"
      ],
      "parents": []
    },
    {
      "uri": "https://data.vlaanderen.be/ns/nutsvoorzieningen#Nutsvoorzieningknoop.zichtbaarheid",
      "name": "zichtbaarheid",
      "label": {
        "fr": "Enter your translation here",
        "nl": "zichtbaarheid"
      },
      "sort": "Enter your translation here",
      "description": {
        "fr": "Enter your translation here",
        "nl": "Mate waarin de Knoop waarneembaar is."
      },
      "usage": {
        "fr": "Enter your translation here",
        "nl": "Bvb nietBovengrondsZichtbaar."
      },
      "domain": [
        "https://data.vlaanderen.be/ns/nutsvoorzieningen#Nutsvoorzieningknoop"
      ],
      "range": [
        "http://www.w3.org/2004/02/skos/core#Concept"
      ],
      "parents": []
    },
    {
      "uri": "https://data.vlaanderen.be/ns/nutsvoorzieningen#Nutsvoorzieningknoop.uiterlijk",
      "name": "uiterlijk",
      "label": {
        "fr": "Enter your translation here",
        "nl": "uiterlijk"
      },
      "sort": "Enter your translation here",
      "description": {
        "fr": "Enter your translation here",
        "nl": "Uitzicht van de Knoop."
      },
      "usage": {
        "fr": "Enter your translation here",
        "nl": "Bvb de kleur."
      },
      "domain": [
        "https://data.vlaanderen.be/ns/nutsvoorzieningen#Nutsvoorzieningknoop"
      ],
      "range": [
        "https://data.vlaanderen.be/ns/nutsvoorzieningen#Uiterlijk"
      ],
      "parents": []
    },
    {
      "uri": "https://data.vlaanderen.be/ns/nutsvoorzieningen#Nutsvoorzieningknoop.risico",
      "name": "risico",
      "label": {
        "fr": "Enter your translation here",
        "nl": "risico"
      },
      "sort": "Enter your translation here",
      "description": {
        "fr": "Enter your translation here",
        "nl": "Geeft aan of de Knoop als gevaarlijk kan beschouwd worden."
      },
      "usage": {},
      "domain": [
        "https://data.vlaanderen.be/ns/nutsvoorzieningen#Nutsvoorzieningknoop"
      ],
      "range": [
        "http://www.w3.org/2004/02/skos/core#Concept"
      ],
      "parents": []
    },
    {
      "uri": "https://data.vlaanderen.be/ns/nutsvoorzieningen#Nutsvoorzieningknoop.orientatie",
      "name": "oriëntatie",
      "label": {
        "fr": "Enter your translation here",
        "nl": "oriëntatie"
      },
      "sort": "Enter your translation here",
      "description": {
        "fr": "Enter your translation here",
        "nl": "Hoek waarmee het symbool dat de Knoop weergeeft op kaart moet worden geroteerd."
      },
      "usage": {},
      "domain": [
        "https://data.vlaanderen.be/ns/nutsvoorzieningen#Nutsvoorzieningknoop"
      ],
      "range": [
        "http://def.isotc211.org/iso19103/2015/MeasureTypes#Measure"
      ],
      "parents": []
    },
    {
      "uri": "https://data.vlaanderen.be/ns/nutsvoorzieningen#Kanaal.pijp",
      "name": "pijp",
      "label": {
        "fr": "Enter your translation here",
        "nl": "pijp"
      },
      "sort": "Enter your translation here",
      "description": {
        "fr": "Enter your translation here",
        "nl": "Pijp gelegen in het Kanaal."
      },
      "usage": {},
      "domain": [
        "https://data.vlaanderen.be/ns/nutsvoorzieningen#Kanaal"
      ],
      "range": [
        "https://data.vlaanderen.be/ns/nutsvoorzieningen#Pijp"
      ],
      "parents": []
    },
    {
      "uri": "https://data.vlaanderen.be/ns/nutsvoorzieningen#Kanaal.kanaal",
      "name": "kanaal",
      "label": {
        "fr": "Enter your translation here",
        "nl": "kanaal"
      },
      "sort": "Enter your translation here",
      "description": {
        "fr": "Enter your translation here",
        "nl": "Kanaal gelegen in het Kanaal."
      },
      "usage": {},
      "domain": [
        "https://data.vlaanderen.be/ns/nutsvoorzieningen#Kanaal"
      ],
      "range": [
        "https://data.vlaanderen.be/ns/nutsvoorzieningen#Kanaal"
      ],
      "parents": []
    },
    {
      "uri": "https://data.vlaanderen.be/ns/nutsvoorzieningen#Kanaal.kabel",
      "name": "kabel",
      "label": {
        "fr": "Enter your translation here",
        "nl": "kabel"
      },
      "sort": "Enter your translation here",
      "description": {
        "fr": "Enter your translation here",
        "nl": "Kabel gelegen in het Kanaal."
      },
      "usage": {},
      "domain": [
        "https://data.vlaanderen.be/ns/nutsvoorzieningen#Kanaal"
      ],
      "range": [
        "https://data.vlaanderen.be/ns/nutsvoorzieningen#Kabel"
      ],
      "parents": []
    },
    {
      "uri": "https://data.vlaanderen.be/ns/nutsvoorzieningen#Kabel.subthema",
      "name": "subthema",
      "label": {
        "fr": "Enter your translation here",
        "nl": "subthema"
      },
      "sort": "Enter your translation here",
      "description": {
        "fr": "Enter your translation here",
        "nl": "Classificatie van een kabel, leiding, of leidingelementen volgens het thematisch domein waar deze toe behoren."
      },
      "usage": {},
      "domain": [
        "https://data.vlaanderen.be/ns/nutsvoorzieningen#Kabel"
      ],
      "range": [
        "http://www.w3.org/2004/02/skos/core#Concept"
      ],
      "parents": []
    },
    {
      "uri": "https://data.vlaanderen.be/ns/nutsvoorzieningen#Activiteitencomplex.inNetwerk",
      "name": "innetwerk",
      "label": {
        "fr": "Enter your translation here",
        "nl": "inNetwerk"
      },
      "sort": "Enter your translation here",
      "description": {
        "fr": "Enter your translation here",
        "nl": "Nutsvoorzieningnetwerk waartoe het complex behoort."
      },
      "usage": {},
      "domain": [
        "https://data.vlaanderen.be/ns/generiek#Activiteitencomplex"
      ],
      "range": [
        "https://data.vlaanderen.be/ns/nutsvoorzieningen#Nutsvoorzieningnetwerk"
      ],
      "parents": []
    },
    {
      "uri": "https://data.vlaanderen.be/ns/nutsvoorzieningen#Aansluiting.toebehorentype",
      "name": "toebehorentype",
      "label": {
        "fr": "Enter your translation here",
        "nl": "toebehorentype"
      },
      "sort": "Enter your translation here",
      "description": {
        "fr": "Enter your translation here",
        "nl": "Aard van het Toebehoren."
      },
      "usage": {
        "fr": "Enter your translation here",
        "nl": "Aansluiting is een specialisatie van Toebehoren waarbij het type Toebehoren \"aansluitingspunt\" is."
      },
      "domain": [
        "https://data.vlaanderen.be/ns/nutsvoorzieningen#Aansluiting"
      ],
      "range": [
        "http://www.w3.org/2004/02/skos/core#Concept"
      ],
      "parents": []
    }
  ],
  "contributors": [],
  "external_terms": [
    {
      "uri": "http://www.w3.org/2004/02/skos/core#Concept",
      "name": "Containertype",
      "label": {
        "fr": "Enter your translation here",
        "nl": "Containertype"
      },
      "description": {
        "fr": "Enter your translation here",
        "nl": "Aard van de container"
      },
      "usage": {},
      "sort": "Enter your translation here",
      "indvl": false,
      "inpackage": false,
      "inscope": true,
      "show": true
    },
    {
      "uri": "http://www.w3.org/2004/02/skos/core#Concept",
      "name": "Zichtbaarheidstype",
      "label": {
        "fr": "Enter your translation here",
        "nl": "Zichtbaarheidstype"
      },
      "description": {
        "fr": "Enter your translation here",
        "nl": "In welke mate het object waarneembaar is."
      },
      "usage": {},
      "sort": "Enter your translation here",
      "indvl": false,
      "inpackage": false,
      "inscope": true,
      "show": true
    },
    {
      "uri": "http://www.w3.org/2004/02/skos/core#Concept",
      "name": "Risicotype",
      "label": {
        "fr": "Enter your translation here",
        "nl": "RisicoType"
      },
      "description": {
        "fr": "Enter your translation here",
        "nl": "De aard van het risico"
      },
      "usage": {},
      "sort": "Enter your translation here",
      "indvl": false,
      "inpackage": false,
      "inscope": true,
      "show": true
    },
    {
      "uri": "http://www.w3.org/2004/02/skos/core#Concept",
      "name": "Kleur",
      "label": {
        "fr": "Enter your translation here",
        "nl": "Kleur"
      },
      "description": {
        "fr": "Enter your translation here",
        "nl": "De kleur van het element"
      },
      "usage": {},
      "sort": "Enter your translation here",
      "indvl": false,
      "inpackage": false,
      "inscope": true,
      "show": true
    },
    {
      "uri": "http://www.w3.org/2004/02/skos/core#Concept",
      "name": "Materiaaltype",
      "label": {
        "fr": "Enter your translation here",
        "nl": "MateriaalType"
      },
      "description": {
        "fr": "Enter your translation here",
        "nl": "De aard van het materiaal"
      },
      "usage": {},
      "sort": "Enter your translation here",
      "indvl": false,
      "inpackage": false,
      "inscope": true,
      "show": true
    },
    {
      "uri": "http://www.w3.org/2004/02/skos/core#Concept",
      "name": "Subthema",
      "label": {
        "fr": "Enter your translation here",
        "nl": "Subthema"
      },
      "description": {
        "fr": "Enter your translation here",
        "nl": "Classificatie van een kabel, leiding, of leidingelementen volgens het thematisch domein waar deze toe behoren."
      },
      "usage": {},
      "sort": "Enter your translation here",
      "indvl": false,
      "inpackage": false,
      "inscope": true,
      "show": true
    },
    {
      "uri": "http://www.w3.org/2004/02/skos/core#Concept",
      "name": "Nutsvoorzieningnetwerktype",
      "label": {
        "fr": "Enter your translation here",
        "nl": "Nutsvoorzieningnetwerktype"
      },
      "description": {
        "fr": "Enter your translation here",
        "nl": "Classificatie van typen nutsvoorzieningnetwerken."
      },
      "usage": {},
      "sort": "Enter your translation here",
      "indvl": false,
      "inpackage": false,
      "inscope": true,
      "show": true
    },
    {
      "uri": "http://www.w3.org/2004/02/skos/core#Concept",
      "name": "Faciliteitstatus",
      "label": {
        "fr": "Enter your translation here",
        "nl": "Faciliteitstatus"
      },
      "description": {
        "fr": "Enter your translation here",
        "nl": "De hoedanigheid van het faciliteitsonderdeel."
      },
      "usage": {},
      "sort": "Enter your translation here",
      "indvl": false,
      "inpackage": false,
      "inscope": true,
      "show": true
    },
    {
      "uri": "http://www.w3.org/2004/02/skos/core#Concept",
      "name": "VerticalePositietype",
      "label": {
        "fr": "Enter your translation here",
        "nl": "Verticale Positietype"
      },
      "description": {
        "fr": "Enter your translation here",
        "nl": "TO DO"
      },
      "usage": {},
      "sort": "Enter your translation here",
      "indvl": false,
      "inpackage": false,
      "inscope": true,
      "show": true
    },
    {
      "uri": "http://www.w3.org/2004/02/skos/core#Concept",
      "name": "Nutsvoorzieningleveringstype",
      "label": {
        "fr": "Enter your translation here",
        "nl": "Nutsvoorzieningleveringstype"
      },
      "description": {
        "fr": "Enter your translation here",
        "nl": "Classificatie van typen nutsvoorzieningsleveringen."
      },
      "usage": {},
      "sort": "Enter your translation here",
      "indvl": false,
      "inpackage": false,
      "inscope": true,
      "show": true
    },
    {
      "uri": "http://www.w3.org/2004/02/skos/core#Concept",
      "name": "Waarschuwingstype",
      "label": {
        "fr": "Enter your translation here",
        "nl": "Waarschuwingstype"
      },
      "description": {
        "fr": "Enter your translation here",
        "nl": "Classificatie van soorten waarschuwingen."
      },
      "usage": {},
      "sort": "Enter your translation here",
      "indvl": false,
      "inpackage": false,
      "inscope": true,
      "show": true
    },
    {
      "uri": "http://www.w3.org/2004/02/skos/core#Concept",
      "name": "Telecommunicatiekabelmateriaaltype",
      "label": {
        "fr": "Enter your translation here",
        "nl": "Telecommunicatiekabelmateriaaltype"
      },
      "description": {
        "fr": "Enter your translation here",
        "nl": "Aard van het materiaal waarvan de Telecommunicatiekabel gemaakt is."
      },
      "usage": {},
      "sort": "Enter your translation here",
      "indvl": false,
      "inpackage": false,
      "inscope": true,
      "show": true
    },
    {
      "uri": "http://www.w3.org/2004/02/skos/core#Concept",
      "name": "Oliegaschemicalientype",
      "label": {
        "fr": "Enter your translation here",
        "nl": "OlieGasChemicalientype"
      },
      "description": {
        "fr": "Enter your translation here",
        "nl": "Classificatie van de olie, gas of chemicaliën."
      },
      "usage": {},
      "sort": "Enter your translation here",
      "indvl": false,
      "inpackage": false,
      "inscope": true,
      "show": true
    },
    {
      "uri": "http://www.w3.org/2004/02/skos/core#Concept",
      "name": "Rioolwatertype",
      "label": {
        "fr": "Enter your translation here",
        "nl": "Rioolwatertype"
      },
      "description": {
        "fr": "Enter your translation here",
        "nl": "Aard van het rioolwater."
      },
      "usage": {},
      "sort": "Enter your translation here",
      "indvl": false,
      "inpackage": false,
      "inscope": true,
      "show": true
    },
    {
      "uri": "http://www.w3.org/2004/02/skos/core#Concept",
      "name": "Watertype",
      "label": {
        "fr": "Enter your translation here",
        "nl": "Watertype"
      },
      "description": {
        "fr": "Enter your translation here",
        "nl": "Aard van het water."
      },
      "usage": {},
      "sort": "Enter your translation here",
      "indvl": false,
      "inpackage": false,
      "inscope": true,
      "show": true
    },
    {
      "uri": "http://www.w3.org/2004/02/skos/core#Concept",
      "name": "ThermischProducttype",
      "label": {
        "fr": "Enter your translation here",
        "nl": "Thermisch Producttype"
      },
      "description": {
        "fr": "Enter your translation here",
        "nl": "Classificatie van het termisch product."
      },
      "usage": {},
      "sort": "Enter your translation here",
      "indvl": false,
      "inpackage": false,
      "inscope": true,
      "show": true
    },
    {
      "uri": "http://www.w3.org/2004/02/skos/core#Concept",
      "name": "Toebehorentype",
      "label": {
        "fr": "Enter your translation here",
        "nl": "Toebehorentype"
      },
      "description": {
        "fr": "Enter your translation here",
        "nl": "Classificatie van de toebehoren."
      },
      "usage": {},
      "sort": "Enter your translation here",
      "indvl": false,
      "inpackage": false,
      "inscope": true,
      "show": true
    },
    {
      "uri": "http://www.w3.org/2004/02/skos/core#Concept",
      "name": "Economischeactiviteittype",
      "label": {
        "fr": "Enter your translation here",
        "nl": "EconomischeActiviteittype"
      },
      "description": {
        "fr": "Enter your translation here",
        "nl": "Classificatie van de economische activiteit."
      },
      "usage": {},
      "sort": "Enter your translation here",
      "indvl": false,
      "inpackage": false,
      "inscope": true,
      "show": true
    },
    {
      "uri": "http://www.w3.org/2004/02/skos/core#Concept",
      "name": "Inputoutputtype",
      "label": {
        "fr": "Enter your translation here",
        "nl": "Inputoutputtype"
      },
      "description": {
        "fr": "Enter your translation here",
        "nl": "De waarde van de input en output."
      },
      "usage": {},
      "sort": "Enter your translation here",
      "indvl": false,
      "inpackage": false,
      "inscope": true,
      "show": true
    },
    {
      "uri": "http://www.w3.org/2004/02/skos/core#Concept",
      "name": "Annotatietype",
      "label": {
        "fr": "Enter your translation here",
        "nl": "Annotatietype"
      },
      "description": {
        "fr": "Enter your translation here",
        "nl": "Aard van de annotatie"
      },
      "usage": {},
      "sort": "Enter your translation here",
      "indvl": false,
      "inpackage": false,
      "inscope": true,
      "show": true
    },
    {
      "uri": "http://www.w3.org/2004/02/skos/core#Concept",
      "name": "Topografischelementtype",
      "label": {
        "fr": "Enter your translation here",
        "nl": "TopografischElementtype"
      },
      "description": {
        "fr": "Enter your translation here",
        "nl": "Classificatie van het topografisch element,"
      },
      "usage": {},
      "sort": "Enter your translation here",
      "indvl": false,
      "inpackage": false,
      "inscope": true,
      "show": true
    },
    {
      "uri": "http://www.w3.org/2004/02/skos/core#Concept",
      "name": "Documentmediumtype",
      "label": {
        "fr": "Enter your translation here",
        "nl": "Documentmediumtype"
      },
      "description": {
        "fr": "Enter your translation here",
        "nl": "Aard van het documentmedium"
      },
      "usage": {},
      "sort": "Enter your translation here",
      "indvl": false,
      "inpackage": false,
      "inscope": true,
      "show": true
    },
    {
      "uri": "http://www.w3.org/2004/02/skos/core#Concept",
      "name": "Documenttype",
      "label": {
        "fr": "Enter your translation here",
        "nl": "Documenttype"
      },
      "description": {
        "fr": "Enter your translation here",
        "nl": "Aard van het document"
      },
      "usage": {},
      "sort": "Enter your translation here",
      "indvl": false,
      "inpackage": false,
      "inscope": true,
      "show": true
    },
    {
      "uri": "http://www.w3.org/2004/02/skos/core#Concept",
      "name": "Referentieoppervlaktype",
      "label": {
        "fr": "Enter your translation here",
        "nl": "Referentieoppervlaktype"
      },
      "description": {
        "fr": "Enter your translation here",
        "nl": "De aard van het referentieoppervlak"
      },
      "usage": {},
      "sort": "Enter your translation here",
      "indvl": false,
      "inpackage": false,
      "inscope": true,
      "show": true
    },
    {
      "uri": "http://www.w3.org/2004/02/skos/core#Concept",
      "name": "Opmetingsmethode",
      "label": {
        "fr": "Enter your translation here",
        "nl": "Opmetingsmethode"
      },
      "description": {
        "fr": "Enter your translation here",
        "nl": "De manier waarop het meetresultaat is vastgestemd"
      },
      "usage": {},
      "sort": "Enter your translation here",
      "indvl": false,
      "inpackage": false,
      "inscope": true,
      "show": true
    },
    {
      "uri": "http://www.w3.org/2004/02/skos/core#Concept",
      "name": "BeschermdGebiedtype",
      "label": {
        "fr": "Enter your translation here",
        "nl": "Beschermd Gebiedtype"
      },
      "description": {
        "fr": "Enter your translation here",
        "nl": "Classificatie van de soorten beschermd gebied"
      },
      "usage": {},
      "sort": "Enter your translation here",
      "indvl": false,
      "inpackage": false,
      "inscope": true,
      "show": true
    },
    {
      "uri": "https://schema.org/height",
      "name": "hoogte",
      "label": {
        "fr": "Enter your translation here",
        "nl": "hoogte"
      },
      "description": {
        "fr": "Enter your translation here",
        "nl": "De hoogte van het Toebehoren."
      },
      "usage": {},
      "sort": "Enter your translation here",
      "inscope": true,
      "indvl": false,
      "inpackage": false,
      "show": true
    },
    {
      "uri": "https://schema.org/height",
      "name": "hoogte",
      "label": {
        "fr": "Enter your translation here",
        "nl": "hoogte"
      },
      "description": {
        "fr": "Enter your translation here",
        "nl": "Afstand boven het Referentieoppervlak."
      },
      "usage": {},
      "sort": "Enter your translation here",
      "inscope": true,
      "indvl": false,
      "inpackage": false,
      "show": true
    },
    {
      "uri": "http://www.w3.org/ns/prov#atLocation",
      "name": "ligging",
      "label": {
        "fr": "Enter your translation here",
        "nl": "ligging"
      },
      "description": {
        "fr": "Enter your translation here",
        "nl": "Locatie van het BeschermdGebied."
      },
      "usage": {},
      "sort": "Enter your translation here",
      "inscope": true,
      "indvl": false,
      "inpackage": false,
      "show": true
    },
    {
      "uri": "http://www.w3.org/ns/locn#geometry",
      "name": "locatie",
      "label": {
        "fr": "Enter your translation here",
        "nl": "locatie"
      },
      "description": {
        "fr": "Enter your translation here",
        "nl": "Geometrie van de Annotatie."
      },
      "usage": {},
      "sort": "Enter your translation here",
      "inscope": true,
      "indvl": false,
      "inpackage": false,
      "show": true
    },
    {
      "uri": "http://www.w3.org/ns/locn#geometry",
      "name": "locatie",
      "label": {
        "fr": "Enter your translation here",
        "nl": "locatie"
      },
      "description": {
        "fr": "Enter your translation here",
        "nl": "Geometrie van het TopografiscElement."
      },
      "usage": {},
      "sort": "Enter your translation here",
      "inscope": true,
      "indvl": false,
      "inpackage": false,
      "show": true
    },
    {
      "uri": "http://www.w3.org/ns/locn#geometry",
      "name": "locatie",
      "label": {
        "fr": "Enter your translation here",
        "nl": "locatie"
      },
      "description": {
        "fr": "Enter your translation here",
        "nl": "Geometrie van de locatie waarop het Plan betrekking heeft."
      },
      "usage": {},
      "sort": "Enter your translation here",
      "inscope": true,
      "indvl": false,
      "inpackage": false,
      "show": true
    },
    {
      "uri": "http://www.w3.org/ns/locn#geometry",
      "name": "ligging",
      "label": {
        "fr": "Enter your translation here",
        "nl": "ligging"
      },
      "description": {
        "fr": "Enter your translation here",
        "nl": "Locatie waarvoor de VerticalePositie geldt."
      },
      "usage": {},
      "sort": "Enter your translation here",
      "inscope": true,
      "indvl": false,
      "inpackage": false,
      "show": true
    },
    {
      "uri": "http://www.w3.org/ns/locn#geometry",
      "name": "ligging",
      "label": {
        "fr": "Enter your translation here",
        "nl": "ligging"
      },
      "description": {
        "fr": "Enter your translation here",
        "nl": "Locatie van het Referentieoppervlak."
      },
      "usage": {},
      "sort": "Enter your translation here",
      "inscope": true,
      "indvl": false,
      "inpackage": false,
      "show": true
    },
    {
      "uri": "http://www.w3.org/ns/locn#geometry",
      "name": "geometrie",
      "label": {
        "fr": "Enter your translation here",
        "nl": "geometrie"
      },
      "description": {
        "fr": "Enter your translation here",
        "nl": "Geometrie van het BeschermdGebied."
      },
      "usage": {},
      "sort": "Enter your translation here",
      "inscope": true,
      "indvl": false,
      "inpackage": false,
      "show": true
    },
    {
      "uri": "http://purl.org/dc/terms/type",
      "name": "containertype",
      "label": {
        "fr": "Enter your translation here",
        "nl": "containertype"
      },
      "description": {
        "fr": "Enter your translation here",
        "nl": "Aard van de Pijp als container."
      },
      "usage": {},
      "sort": "Enter your translation here",
      "inscope": true,
      "indvl": false,
      "inpackage": false,
      "show": true
    },
    {
      "uri": "http://purl.org/dc/terms/type",
      "name": "containertype",
      "label": {
        "fr": "Enter your translation here",
        "nl": "containertype"
      },
      "description": {
        "fr": "Enter your translation here",
        "nl": "Aard van het Kanaal als container."
      },
      "usage": {},
      "sort": "Enter your translation here",
      "inscope": true,
      "indvl": false,
      "inpackage": false,
      "show": true
    },
    {
      "uri": "http://purl.org/dc/elements/1.1/type",
      "name": "type",
      "label": {
        "fr": "Enter your translation here",
        "nl": "type"
      },
      "description": {
        "fr": "Enter your translation here",
        "nl": "Type referentieoppervlak."
      },
      "usage": {},
      "sort": "Enter your translation here",
      "inscope": true,
      "indvl": false,
      "inpackage": false,
      "show": true
    },
    {
      "uri": "http://purl.org/dc/elements/1.1/type",
      "name": "type",
      "label": {
        "fr": "Enter your translation here",
        "nl": "type"
      },
      "description": {
        "fr": "Enter your translation here",
        "nl": "Aard van het BeschermdGebied."
      },
      "usage": {},
      "sort": "Enter your translation here",
      "inscope": true,
      "indvl": false,
      "inpackage": false,
      "show": true
    },
    {
      "uri": "http://purl.org/dc/elements/1.1/type",
      "name": "topografischElementtype",
      "label": {
        "fr": "Enter your translation here",
        "nl": "topografisch elementtype"
      },
      "description": {
        "fr": "Enter your translation here",
        "nl": "Aard van het TopografischElement."
      },
      "usage": {},
      "sort": "Enter your translation here",
      "inscope": true,
      "indvl": false,
      "inpackage": false,
      "show": true
    },
    {
      "uri": "http://purl.org/dc/elements/1.1/type",
      "name": "toebehorentype",
      "label": {
        "fr": "Enter your translation here",
        "nl": "toebehorentype"
      },
      "description": {
        "fr": "Enter your translation here",
        "nl": "Type van Toebehoren."
      },
      "usage": {},
      "sort": "Enter your translation here",
      "inscope": true,
      "indvl": false,
      "inpackage": false,
      "show": true
    },
    {
      "uri": "http://purl.org/dc/elements/1.1/type",
      "name": "nutsvoorzieningnetwerktype",
      "label": {
        "fr": "Enter your translation here",
        "nl": "nutsvoorzieningnetwerktype"
      },
      "description": {
        "fr": "Enter your translation here",
        "nl": "Het type nutsvoorzieningnetwerk of het thema van het nutsvoorzieningnetwerk."
      },
      "usage": {},
      "sort": "Enter your translation here",
      "inscope": true,
      "indvl": false,
      "inpackage": false,
      "show": true
    },
    {
      "uri": "http://purl.org/dc/elements/1.1/type",
      "name": "annotatietype",
      "label": {
        "fr": "Enter your translation here",
        "nl": "annotatietype"
      },
      "description": {
        "fr": "Enter your translation here",
        "nl": "Aard van de Annotatie."
      },
      "usage": {},
      "sort": "Enter your translation here",
      "inscope": true,
      "indvl": false,
      "inpackage": false,
      "show": true
    },
    {
      "uri": "http://purl.org/dc/elements/1.1/title",
      "name": "naam",
      "label": {
        "fr": "Enter your translation here",
        "nl": "naam"
      },
      "description": {
        "fr": "Enter your translation here",
        "nl": "Naam van het BeschermdGebied."
      },
      "usage": {},
      "sort": "Enter your translation here",
      "inscope": true,
      "indvl": false,
      "inpackage": false,
      "show": true
    },
    {
      "uri": "http://purl.org/dc/elements/1.1/relation",
      "name": "documentatie",
      "label": {
        "fr": "Enter your translation here",
        "nl": "documentatie"
      },
      "description": {
        "fr": "Enter your translation here",
        "nl": "Verwijzing naar een Document met extra informatie over het element."
      },
      "usage": {},
      "sort": "Enter your translation here",
      "inscope": true,
      "indvl": false,
      "inpackage": false,
      "show": true
    },
    {
      "uri": "http://purl.org/dc/elements/1.1/relation",
      "name": "documentatie",
      "label": {
        "fr": "Enter your translation here",
        "nl": "documentatie"
      },
      "description": {
        "fr": "Enter your translation here",
        "nl": "Verwijzing naar een Document met extra informatie over het Netwerk."
      },
      "usage": {},
      "sort": "Enter your translation here",
      "inscope": true,
      "indvl": false,
      "inpackage": false,
      "show": true
    },
    {
      "uri": "http://purl.org/dc/elements/1.1/description",
      "name": "beschrijving",
      "label": {
        "fr": "Enter your translation here",
        "nl": "beschrijving"
      },
      "description": {
        "fr": "Enter your translation here",
        "nl": "Beschrijving van het BeschermdGebied."
      },
      "usage": {},
      "sort": "Enter your translation here",
      "inscope": true,
      "indvl": false,
      "inpackage": false,
      "show": true
    },
    {
      "uri": "http://purl.org/dc/elements/1.1/date",
      "name": "datum",
      "label": {
        "fr": "Enter your translation here",
        "nl": "datum"
      },
      "description": {
        "fr": "Enter your translation here",
        "nl": "Het moment waarop de Opmeting heeft plaatsgevonden"
      },
      "usage": {},
      "sort": "Enter your translation here",
      "inscope": true,
      "indvl": false,
      "inpackage": false,
      "show": true
    }
  ],
  "documentroot": "/doc/vocabularium/nutsvoorzieningen/kandidaatstandaard/2024-01-26"
}
